[
  {
    "id": "66b4501d942c7eb28beebb97",
    "periodId": "modern_early",
    "streamId": "s_modern_early",
    "titleEn": "吴隐辑、吴昌硕刻印成《缶庐印存》四册",
    "titleCn": "吴隐辑、吴昌硕刻印成《缶庐印存》四册",
    "date": {
      "year": 1900
    },
    "importance": 4,
    "tags": [
      "近代",
      "书法事件 / Calligraphy Event"
    ],
    "meta": {
      "dynasty": "近代",
      "traditionalDate": "光绪二十六年",
      "person": "吴隐、吴昌硕",
      "style": "书法事件 / Calligraphy Event",
      "sourceOrder": 1709
    },
    "creatorCn": "吴隐、吴昌硕",
    "imageUrl": "https://yishuwiki.oss-cn-beijing.aliyuncs.com/Operator/HistoricalEvent/2024/11/20241126164355324.png"
  },
  {
    "id": "66b4501d942c7eb28beebb98",
    "periodId": "modern_early",
    "streamId": "s_modern_early",
    "titleEn": "陈宝琛辑《澂秋馆封泥考存》",
    "titleCn": "陈宝琛辑《澂秋馆封泥考存》",
    "date": {
      "year": 1900
    },
    "importance": 4,
    "tags": [
      "近代",
      "书法事件 / Calligraphy Event"
    ],
    "meta": {
      "dynasty": "近代",
      "traditionalDate": "光绪二十六年",
      "person": "陈宝琛",
      "style": "书法事件 / Calligraphy Event",
      "sourceOrder": 1710
    },
    "creatorCn": "陈宝琛",
    "imageUrl": "https://yishuwiki.oss-cn-beijing.aliyuncs.com/Operator/HistoricalEvent/2024/09/20240911105930282.png"
  },
  {
    "id": "66b4501d942c7eb28beebb99",
    "periodId": "modern_early",
    "streamId": "s_modern_early",
    "titleEn": "敦煌千佛洞发现大量敦煌遗书",
    "titleCn": "敦煌千佛洞发现大量敦煌遗书",
    "date": {
      "year": 1900
    },
    "importance": 4,
    "tags": [
      "近代",
      "楷书 / Regular Script"
    ],
    "meta": {
      "dynasty": "近代",
      "traditionalDate": "光绪二十六年",
      "person": "斯坦因、伯希和",
      "style": "楷书 / Regular Script",
      "sourceOrder": 1711
    },
    "creatorCn": "斯坦因、伯希和",
    "imageUrl": "https://yishuwiki.oss-cn-beijing.aliyuncs.com/Operator/HistoricalEvent/2024/09/20240911111220415.png",
    "descriptionCn": "敦煌千佛洞发现《敦煌石室写经》，宋搨唐太宗书《温泉铭》、欧阳询书《化度寺碑》、柳公权书《金刚经》、唐人书《陀罗尼经》四种，先后为英国人斯坦因、法国人伯希和买走。"
  },
  {
    "id": "66b4501d942c7eb28beebb9a",
    "periodId": "modern_early",
    "streamId": "s_modern_early",
    "titleEn": "杨守敬书《隶书七言联》",
    "titleCn": "杨守敬书《隶书七言联》",
    "date": {
      "year": 1900
    },
    "importance": 4,
    "tags": [
      "近代",
      "隶书与汉碑 / Clerical Script"
    ],
    "meta": {
      "dynasty": "近代",
      "traditionalDate": "光绪二十六年",
      "person": "杨守敬",
      "style": "隶书与汉碑 / Clerical Script",
      "sourceOrder": 1712
    },
    "creatorCn": "杨守敬",
    "imageUrl": "https://yishuwiki.oss-cn-beijing.aliyuncs.com/Operator/HistoricalEvent/2024/09/20240911111337303.png"
  },
  {
    "id": "66b4501d942c7eb28beebb9b",
    "periodId": "modern_early",
    "streamId": "s_modern_early",
    "titleEn": "李叔同（弘一法师）书《李庐印谱》",
    "titleCn": "李叔同（弘一法师）书《李庐印谱》",
    "date": {
      "year": 1901
    },
    "importance": 4,
    "tags": [
      "近代",
      "篆刻与印学 / Seal Carving"
    ],
    "meta": {
      "dynasty": "近代",
      "traditionalDate": "光绪二十七年",
      "person": "李叔同",
      "style": "篆刻与印学 / Seal Carving",
      "sourceOrder": 1713
    },
    "creatorCn": "李叔同",
    "imageUrl": "https://yishuwiki.oss-cn-beijing.aliyuncs.com/Operator/HistoricalEvent/2024/11/20241126161249173.png"
  },
  {
    "id": "66b4501d942c7eb28beebb9c",
    "periodId": "modern_early",
    "streamId": "s_modern_early",
    "titleEn": "方介堪出生",
    "titleCn": "方介堪出生",
    "date": {
      "year": 1901
    },
    "importance": 4,
    "tags": [
      "近代",
      "书法事件 / Calligraphy Event"
    ],
    "meta": {
      "dynasty": "近代",
      "traditionalDate": "光绪二十七年",
      "person": "方介堪",
      "style": "书法事件 / Calligraphy Event",
      "sourceOrder": 1714
    },
    "creatorCn": "方介堪",
    "imageUrl": "https://yishuwiki.oss-cn-beijing.aliyuncs.com/Operator/HistoricalEvent/2024/09/20240911112408177.png",
    "descriptionCn": "方介堪卒于公元1987年，时年八十六岁。"
  },
  {
    "id": "66b4501d942c7eb28beebb9d",
    "periodId": "modern_early",
    "streamId": "s_modern_early",
    "titleEn": "英国人斯坦因得汉晋木简",
    "titleCn": "英国人斯坦因得汉晋木简",
    "date": {
      "year": 1901
    },
    "importance": 4,
    "tags": [
      "近代",
      "书法事件 / Calligraphy Event"
    ],
    "meta": {
      "dynasty": "近代",
      "traditionalDate": "光绪二十七年",
      "person": "斯坦因",
      "style": "书法事件 / Calligraphy Event",
      "sourceOrder": 1715
    },
    "creatorCn": "斯坦因",
    "imageUrl": "https://yishuwiki.oss-cn-beijing.aliyuncs.com/Operator/HistoricalEvent/2024/09/20240911112838469.png",
    "descriptionCn": "英国人斯坦因先后在新疆古于阗、楼兰遗址得汉晋木简六十余枚。"
  },
  {
    "id": "66b4501d942c7eb28beebb9e",
    "periodId": "modern_early",
    "streamId": "s_modern_early",
    "titleEn": "齐白石书《仿八大山人画识语扇面》",
    "titleCn": "齐白石书《仿八大山人画识语扇面》",
    "date": {
      "year": 1902
    },
    "importance": 4,
    "tags": [
      "近代",
      "书法事件 / Calligraphy Event"
    ],
    "meta": {
      "dynasty": "近代",
      "traditionalDate": "光绪二十八年",
      "person": "齐白石",
      "style": "书法事件 / Calligraphy Event",
      "sourceOrder": 1716
    },
    "creatorCn": "齐白石",
    "imageUrl": "https://yishuwiki.oss-cn-beijing.aliyuncs.com/Operator/HistoricalEvent/2024/09/20240911114247386.png"
  },
  {
    "id": "66b4501d942c7eb28beebb9f",
    "periodId": "modern_early",
    "streamId": "s_modern_early",
    "titleEn": "叶铭辑、赵之谦刻印成《二金蜨堂印谱》四册",
    "titleCn": "叶铭辑、赵之谦刻印成《二金蜨堂印谱》四册",
    "date": {
      "year": 1902
    },
    "importance": 4,
    "tags": [
      "近代",
      "篆刻与印学 / Seal Carving"
    ],
    "meta": {
      "dynasty": "近代",
      "traditionalDate": "光绪二十八年",
      "person": "叶铭、赵之谦",
      "style": "篆刻与印学 / Seal Carving",
      "sourceOrder": 1717
    },
    "creatorCn": "叶铭、赵之谦",
    "imageUrl": "https://yishuwiki.oss-cn-beijing.aliyuncs.com/Operator/HistoricalEvent/2024/11/20241126164645204.png"
  },
  {
    "id": "66b4501d942c7eb28beebba0",
    "periodId": "modern_early",
    "streamId": "s_modern_early",
    "titleEn": "高二适出生",
    "titleCn": "高二适出生",
    "date": {
      "year": 1903
    },
    "importance": 4,
    "tags": [
      "近代",
      "书法事件 / Calligraphy Event"
    ],
    "meta": {
      "dynasty": "近代",
      "traditionalDate": "光绪二十九年",
      "person": "高二适",
      "style": "书法事件 / Calligraphy Event",
      "sourceOrder": 1718
    },
    "creatorCn": "高二适",
    "imageUrl": "https://yishuwiki.oss-cn-beijing.aliyuncs.com/Operator/HistoricalEvent/2024/09/20240911123052285.png",
    "descriptionCn": "高二适卒于公元1963年，时年七十四岁。"
  },
  {
    "id": "66b4501d942c7eb28beebba1",
    "periodId": "modern_early",
    "streamId": "s_modern_early",
    "titleEn": "来楚生出生",
    "titleCn": "来楚生出生",
    "date": {
      "year": 1903
    },
    "importance": 4,
    "tags": [
      "近代",
      "书法事件 / Calligraphy Event"
    ],
    "meta": {
      "dynasty": "近代",
      "traditionalDate": "光绪二十九年",
      "person": "来楚生",
      "style": "书法事件 / Calligraphy Event",
      "sourceOrder": 1719
    },
    "creatorCn": "来楚生",
    "imageUrl": "https://yishuwiki.oss-cn-beijing.aliyuncs.com/Operator/HistoricalEvent/2024/09/20240911123129725.png",
    "descriptionCn": "来楚生卒于公元1975年，时年七十二岁。"
  },
  {
    "id": "66b4501d942c7eb28beebba2",
    "periodId": "modern_early",
    "streamId": "s_modern_early",
    "titleEn": "刘鹗首次著录甲骨文搨片",
    "titleCn": "刘鹗首次著录甲骨文搨片",
    "date": {
      "year": 1903
    },
    "importance": 1,
    "tags": [
      "近代",
      "甲骨文 / Oracle-bone Script"
    ],
    "meta": {
      "dynasty": "近代",
      "traditionalDate": "光绪二十九年",
      "person": "刘鹗",
      "style": "甲骨文 / Oracle-bone Script",
      "sourceOrder": 1720
    },
    "creatorCn": "刘鹗",
    "imageUrl": "https://yishuwiki.oss-cn-beijing.aliyuncs.com/Operator/HistoricalEvent/2024/09/20240911123341313.png",
    "descriptionCn": "刘鹗（铁云）首次著录甲骨文搨片一千零五十八纸为《铁云藏龟》六册行世。"
  },
  {
    "id": "66b4501d942c7eb28beebba3",
    "periodId": "modern_early",
    "streamId": "s_modern_early",
    "titleEn": "孙诒让首撰《契文举例》",
    "titleCn": "孙诒让首撰《契文举例》",
    "date": {
      "year": 1904
    },
    "importance": 4,
    "tags": [
      "近代",
      "甲骨文 / Oracle-bone Script"
    ],
    "meta": {
      "dynasty": "近代",
      "traditionalDate": "光绪三十年",
      "person": "孙诒让",
      "style": "甲骨文 / Oracle-bone Script",
      "sourceOrder": 1721
    },
    "creatorCn": "孙诒让",
    "imageUrl": "https://yishuwiki.oss-cn-beijing.aliyuncs.com/Operator/HistoricalEvent/2024/09/20240911123535357.png",
    "descriptionCn": "孙诒让首撰甲骨文字考释专著《契文举例》书成。"
  },
  {
    "id": "66b4501d942c7eb28beebba4",
    "periodId": "modern_early",
    "streamId": "s_modern_early",
    "titleEn": "西泠印社创立",
    "titleCn": "西泠印社创立",
    "date": {
      "year": 1904
    },
    "importance": 4,
    "tags": [
      "近代",
      "书法事件 / Calligraphy Event"
    ],
    "meta": {
      "dynasty": "近代",
      "traditionalDate": "光绪三十年",
      "person": "吴隐、丁仁、王禔、叶名",
      "style": "书法事件 / Calligraphy Event",
      "sourceOrder": 1722
    },
    "creatorCn": "吴隐、丁仁、王禔、叶名",
    "imageUrl": "https://yishuwiki.oss-cn-beijing.aliyuncs.com/Operator/HistoricalEvent/2024/09/20240911123754174.png",
    "descriptionCn": "吴隐、丁仁、王禔、叶名等于杭州孤山创立西泠印社。"
  },
  {
    "id": "66b4501d942c7eb28beebba5",
    "periodId": "modern_early",
    "streamId": "s_modern_early",
    "titleEn": "西泠印社辑吴熙载刻印成《吴让之印存》十册",
    "titleCn": "西泠印社辑吴熙载刻印成《吴让之印存》十册",
    "date": {
      "year": 1904
    },
    "importance": 4,
    "tags": [
      "近代",
      "书法事件 / Calligraphy Event"
    ],
    "meta": {
      "dynasty": "近代",
      "traditionalDate": "光绪三十年",
      "person": "吴熙载",
      "style": "书法事件 / Calligraphy Event",
      "sourceOrder": 1723
    },
    "creatorCn": "吴熙载",
    "imageUrl": "https://yishuwiki.oss-cn-beijing.aliyuncs.com/Operator/HistoricalEvent/2024/09/20240911124107695.png"
  },
  {
    "id": "66b4501d942c7eb28beebba6",
    "periodId": "modern_early",
    "streamId": "s_modern_early",
    "titleEn": "吴昌硕书《临庚赢卣铭文轴》",
    "titleCn": "吴昌硕书《临庚赢卣铭文轴》",
    "date": {
      "year": 1905
    },
    "importance": 4,
    "tags": [
      "近代",
      "金文 / Bronze Script"
    ],
    "meta": {
      "dynasty": "近代",
      "traditionalDate": "光绪三十一年",
      "person": "吴昌硕",
      "style": "金文 / Bronze Script",
      "sourceOrder": 1724
    },
    "creatorCn": "吴昌硕",
    "imageUrl": "https://yishuwiki.oss-cn-beijing.aliyuncs.com/Operator/HistoricalEvent/2024/09/20240911124428306.jpeg"
  },
  {
    "id": "66b4501d942c7eb28beebba7",
    "periodId": "modern_early",
    "streamId": "s_modern_early",
    "titleEn": "潘伯鹰出生",
    "titleCn": "潘伯鹰出生",
    "date": {
      "year": 1905
    },
    "importance": 4,
    "tags": [
      "近代",
      "书法事件 / Calligraphy Event"
    ],
    "meta": {
      "dynasty": "近代",
      "traditionalDate": "光绪三十一年",
      "person": "潘伯鹰",
      "style": "书法事件 / Calligraphy Event",
      "sourceOrder": 1725
    },
    "creatorCn": "潘伯鹰",
    "imageUrl": "https://yishuwiki.oss-cn-beijing.aliyuncs.com/Operator/HistoricalEvent/2024/09/20240911124154121.png",
    "descriptionCn": "潘伯鹰卒于公元1966年，时年六十一岁。"
  },
  {
    "id": "66b4501d942c7eb28beebba8",
    "periodId": "modern_early",
    "streamId": "s_modern_early",
    "titleEn": "潘伯鹰撰《潘伯鹰墨迹选》",
    "titleCn": "潘伯鹰撰《潘伯鹰墨迹选》",
    "date": {
      "year": 1905
    },
    "importance": 4,
    "tags": [
      "近代",
      "书论与收藏 / Theory and Connoisseurship"
    ],
    "meta": {
      "dynasty": "近代",
      "traditionalDate": "",
      "person": "潘伯鹰",
      "style": "书论与收藏 / Theory and Connoisseurship",
      "sourceOrder": 1726
    },
    "endDate": {
      "year": 1966
    },
    "creatorCn": "潘伯鹰",
    "imageUrl": "https://yishuwiki.oss-cn-beijing.aliyuncs.com/Operator/HistoricalEvent/2024/09/20240911124551080.png"
  },
  {
    "id": "66b4501d942c7eb28beebba9",
    "periodId": "modern_early",
    "streamId": "s_modern_early",
    "titleEn": "罗振玉、王国维撰《流沙坠简》",
    "titleCn": "罗振玉、王国维撰《流沙坠简》",
    "date": {
      "year": 1906
    },
    "importance": 4,
    "tags": [
      "近代",
      "书论与收藏 / Theory and Connoisseurship"
    ],
    "meta": {
      "dynasty": "近代",
      "traditionalDate": "光绪三十二年",
      "person": "罗振玉、王国维",
      "style": "书论与收藏 / Theory and Connoisseurship",
      "sourceOrder": 1727
    },
    "endDate": {
      "year": 1908
    },
    "creatorCn": "罗振玉、王国维",
    "imageUrl": "https://yishuwiki.oss-cn-beijing.aliyuncs.com/Operator/HistoricalEvent/2024/09/20240911141521578.png",
    "descriptionCn": "甘肃敦煌西北古长城遗址出土大批汉晋木简，罗振玉、王国维因之撰《流沙坠简》。"
  },
  {
    "id": "66b4501d942c7eb28beebbaa",
    "periodId": "modern_early",
    "streamId": "s_modern_early",
    "titleEn": "震钧撰《国朝书人辑略》",
    "titleCn": "震钧撰《国朝书人辑略》",
    "date": {
      "year": 1907
    },
    "importance": 4,
    "tags": [
      "近代",
      "书论与收藏 / Theory and Connoisseurship"
    ],
    "meta": {
      "dynasty": "近代",
      "traditionalDate": "光绪三十三年",
      "person": "震钧",
      "style": "书论与收藏 / Theory and Connoisseurship",
      "sourceOrder": 1728
    },
    "creatorCn": "震钧",
    "imageUrl": "https://yishuwiki.oss-cn-beijing.aliyuncs.com/Operator/HistoricalEvent/2024/11/20241126164831766.png"
  },
  {
    "id": "66b4501d942c7eb28beebbab",
    "periodId": "modern_early",
    "streamId": "s_modern_early",
    "titleEn": "白蕉出生",
    "titleCn": "白蕉出生",
    "date": {
      "year": 1907
    },
    "importance": 4,
    "tags": [
      "近代",
      "书法事件 / Calligraphy Event"
    ],
    "meta": {
      "dynasty": "近代",
      "traditionalDate": "光绪三十三年",
      "person": "白蕉",
      "style": "书法事件 / Calligraphy Event",
      "sourceOrder": 1729
    },
    "creatorCn": "白蕉",
    "imageUrl": "https://yishuwiki.oss-cn-beijing.aliyuncs.com/Operator/HistoricalEvent/2024/09/20240911142051772.png",
    "descriptionCn": "白蕉卒于公元1969年，时年六十二岁。"
  },
  {
    "id": "66b4501d942c7eb28beebbac",
    "periodId": "modern_early",
    "streamId": "s_modern_early",
    "titleEn": "赵之琛刻印《赵次闲印存》",
    "titleCn": "赵之琛刻印《赵次闲印存》",
    "date": {
      "year": 1908
    },
    "importance": 4,
    "tags": [
      "近代",
      "书法事件 / Calligraphy Event"
    ],
    "meta": {
      "dynasty": "近代",
      "traditionalDate": "光绪三十四年",
      "person": "赵之琛",
      "style": "书法事件 / Calligraphy Event",
      "sourceOrder": 1730
    },
    "creatorCn": "赵之琛",
    "imageUrl": "https://yishuwiki.oss-cn-beijing.aliyuncs.com/Operator/HistoricalEvent/2024/09/20240911143239898.png",
    "descriptionCn": "西泠印社辑赵之琛刻印成《赵次闲印存》四册"
  },
  {
    "id": "66b4501d942c7eb28beebbad",
    "periodId": "modern_early",
    "streamId": "s_modern_early",
    "titleEn": "钱松刻印《钱叔盖印谱》",
    "titleCn": "钱松刻印《钱叔盖印谱》",
    "date": {
      "year": 1908
    },
    "importance": 4,
    "tags": [
      "近代",
      "篆刻与印学 / Seal Carving"
    ],
    "meta": {
      "dynasty": "近代",
      "traditionalDate": "光绪三十四年",
      "person": "钱松",
      "style": "篆刻与印学 / Seal Carving",
      "sourceOrder": 1731
    },
    "creatorCn": "钱松",
    "imageUrl": "https://yishuwiki.oss-cn-beijing.aliyuncs.com/Operator/HistoricalEvent/2024/11/20241126161453109.png",
    "descriptionCn": "金莺山房辑钱松刻印成《钱叔盖印谱》六册"
  },
  {
    "id": "66b4501d942c7eb28beebbae",
    "periodId": "modern_early",
    "streamId": "s_modern_early",
    "titleEn": "山东东平出土汉《张表造虎函刻石》",
    "titleCn": "山东东平出土汉《张表造虎函刻石》",
    "date": {
      "year": 1908
    },
    "importance": 4,
    "tags": [
      "近代",
      "书法事件 / Calligraphy Event"
    ],
    "meta": {
      "dynasty": "近代",
      "traditionalDate": "光绪三十四年",
      "person": "",
      "style": "书法事件 / Calligraphy Event",
      "sourceOrder": 1732
    },
    "imageUrl": "https://yishuwiki.oss-cn-beijing.aliyuncs.com/Operator/HistoricalEvent/2024/09/20240911143843244.png"
  },
  {
    "id": "66b4501e942c7eb28beebbaf",
    "periodId": "modern_early",
    "streamId": "s_modern_early",
    "titleEn": "叶昌炽《语石》刊行",
    "titleCn": "叶昌炽《语石》刊行",
    "date": {
      "year": 1909
    },
    "importance": 4,
    "tags": [
      "近代",
      "书法事件 / Calligraphy Event"
    ],
    "meta": {
      "dynasty": "近代",
      "traditionalDate": "宣统元年",
      "person": "叶昌炽",
      "style": "书法事件 / Calligraphy Event",
      "sourceOrder": 1733
    },
    "creatorCn": "叶昌炽",
    "imageUrl": "https://yishuwiki.oss-cn-beijing.aliyuncs.com/Operator/HistoricalEvent/2024/11/20241126164604182.png"
  },
  {
    "id": "66b4501e942c7eb28beebbb0",
    "periodId": "modern_early",
    "streamId": "s_modern_early",
    "titleEn": "吴昌硕书《临石鼓文赠澹如先生轴》",
    "titleCn": "吴昌硕书《临石鼓文赠澹如先生轴》",
    "date": {
      "year": 1909
    },
    "importance": 1,
    "tags": [
      "近代",
      "篆书 / Seal Script"
    ],
    "meta": {
      "dynasty": "近代",
      "traditionalDate": "宣统元年",
      "person": "吴昌硕",
      "style": "篆书 / Seal Script",
      "sourceOrder": 1734
    },
    "creatorCn": "吴昌硕",
    "imageUrl": "https://yishuwiki.oss-cn-beijing.aliyuncs.com/Operator/HistoricalEvent/2024/09/20240911145157027.png"
  },
  {
    "id": "66b4501e942c7eb28beebbb1",
    "periodId": "modern_early",
    "streamId": "s_modern_early",
    "titleEn": "叶铭撰《再续印人传》三卷及补遗一卷",
    "titleCn": "叶铭撰《再续印人传》三卷及补遗一卷",
    "date": {
      "year": 1910
    },
    "importance": 4,
    "tags": [
      "近代",
      "书论与收藏 / Theory and Connoisseurship"
    ],
    "meta": {
      "dynasty": "近代",
      "traditionalDate": "宣统二年",
      "person": "叶铭",
      "style": "书论与收藏 / Theory and Connoisseurship",
      "sourceOrder": 1735
    },
    "creatorCn": "叶铭",
    "imageUrl": "https://yishuwiki.oss-cn-beijing.aliyuncs.com/Operator/HistoricalEvent/2024/09/20240911145306098.png"
  },
  {
    "id": "66b4501e942c7eb28beebbb2",
    "periodId": "modern_early",
    "streamId": "s_modern_early",
    "titleEn": "西泠印社辑《印汇》",
    "titleCn": "西泠印社辑《印汇》",
    "date": {
      "year": 1910
    },
    "importance": 4,
    "tags": [
      "近代",
      "书法事件 / Calligraphy Event"
    ],
    "meta": {
      "dynasty": "近代",
      "traditionalDate": "宣统二年",
      "person": "",
      "style": "书法事件 / Calligraphy Event",
      "sourceOrder": 1736
    },
    "imageUrl": "https://yishuwiki.oss-cn-beijing.aliyuncs.com/Operator/HistoricalEvent/2024/09/20240911145853230.png",
    "descriptionCn": "西泠印社辑《印汇》百五十二册本"
  },
  {
    "id": "66b4501e942c7eb28beebbb3",
    "periodId": "modern_early",
    "streamId": "s_modern_early",
    "titleEn": "西泠印社辑《龙泓山人印谱》",
    "titleCn": "西泠印社辑《龙泓山人印谱》",
    "date": {
      "year": 1910
    },
    "importance": 4,
    "tags": [
      "近代",
      "篆刻与印学 / Seal Carving"
    ],
    "meta": {
      "dynasty": "近代",
      "traditionalDate": "宣统二年",
      "person": "丁敬",
      "style": "篆刻与印学 / Seal Carving",
      "sourceOrder": 1737
    },
    "creatorCn": "丁敬",
    "imageUrl": "https://yishuwiki.oss-cn-beijing.aliyuncs.com/Operator/HistoricalEvent/2024/09/20240911150150011.png",
    "descriptionCn": "西泠印社丁敬刻印成《龙泓山人印谱》二册"
  },
  {
    "id": "66b4501e942c7eb28beebbb4",
    "periodId": "modern_early",
    "streamId": "s_modern_early",
    "titleEn": "端方书《行楷七方联》",
    "titleCn": "端方书《行楷七方联》",
    "date": {
      "year": 1910
    },
    "importance": 4,
    "tags": [
      "近代",
      "楷书 / Regular Script"
    ],
    "meta": {
      "dynasty": "近代",
      "traditionalDate": "宣统二年",
      "person": "端方",
      "style": "楷书 / Regular Script",
      "sourceOrder": 1738
    },
    "creatorCn": "端方",
    "imageUrl": "https://yishuwiki.oss-cn-beijing.aliyuncs.com/Operator/HistoricalEvent/2024/09/20240911153323421.png"
  },
  {
    "id": "66b4501e942c7eb28beebbb5",
    "periodId": "modern_early",
    "streamId": "s_modern_early",
    "titleEn": "罗振玉著《殷商贞卜文字考》",
    "titleCn": "罗振玉著《殷商贞卜文字考》",
    "date": {
      "year": 1910
    },
    "importance": 4,
    "tags": [
      "近代",
      "书论与收藏 / Theory and Connoisseurship"
    ],
    "meta": {
      "dynasty": "近代",
      "traditionalDate": "宣统二年",
      "person": "罗振玉",
      "style": "书论与收藏 / Theory and Connoisseurship",
      "sourceOrder": 1739
    },
    "creatorCn": "罗振玉",
    "imageUrl": "https://yishuwiki.oss-cn-beijing.aliyuncs.com/Operator/HistoricalEvent/2024/09/20240911154139688.png"
  },
  {
    "id": "66b4501e942c7eb28beebbb6",
    "periodId": "modern_early",
    "streamId": "s_modern_early",
    "titleEn": "西泠印社辑奚冈刻印成《蒙泉外史印谱》二册",
    "titleCn": "西泠印社辑奚冈刻印成《蒙泉外史印谱》二册",
    "date": {
      "year": 1911
    },
    "importance": 4,
    "tags": [
      "近代",
      "篆刻与印学 / Seal Carving"
    ],
    "meta": {
      "dynasty": "近代",
      "traditionalDate": "宣统三年",
      "person": "奚冈",
      "style": "篆刻与印学 / Seal Carving",
      "sourceOrder": 1740
    },
    "creatorCn": "奚冈",
    "imageUrl": "https://yishuwiki.oss-cn-beijing.aliyuncs.com/Operator/HistoricalEvent/2024/09/20240911154246498.png"
  },
  {
    "id": "66b4501e942c7eb28beebbb7",
    "periodId": "modern_early",
    "streamId": "s_modern_early",
    "titleEn": "有正书局选辑《邓石如印存》二册本",
    "titleCn": "有正书局选辑《邓石如印存》二册本",
    "date": {
      "year": 1911
    },
    "importance": 4,
    "tags": [
      "近代",
      "书法事件 / Calligraphy Event"
    ],
    "meta": {
      "dynasty": "近代",
      "traditionalDate": "宣统三年",
      "person": "邓石如",
      "style": "书法事件 / Calligraphy Event",
      "sourceOrder": 1741
    },
    "creatorCn": "邓石如",
    "imageUrl": "https://yishuwiki.oss-cn-beijing.aliyuncs.com/Operator/HistoricalEvent/2024/09/20240911160152254.png"
  },
  {
    "id": "66b4501e942c7eb28beebbb8",
    "periodId": "modern_early",
    "streamId": "s_modern_early",
    "titleEn": "西泠印社辑蒋仁刻印成《吉罗居士印谱》二册",
    "titleCn": "西泠印社辑蒋仁刻印成《吉罗居士印谱》二册",
    "date": {
      "year": 1911
    },
    "importance": 4,
    "tags": [
      "近代",
      "篆刻与印学 / Seal Carving"
    ],
    "meta": {
      "dynasty": "近代",
      "traditionalDate": "宣统三年",
      "person": "蒋仁刻",
      "style": "篆刻与印学 / Seal Carving",
      "sourceOrder": 1742
    },
    "creatorCn": "蒋仁刻",
    "imageUrl": "https://yishuwiki.oss-cn-beijing.aliyuncs.com/Operator/HistoricalEvent/2024/11/20241126164507609.png"
  },
  {
    "id": "66b4501e942c7eb28beebbb9",
    "periodId": "modern_early",
    "streamId": "s_modern_early",
    "titleEn": "有正书局辑徐三庚刻印《金罍山民手刻印存》四册",
    "titleCn": "有正书局辑徐三庚刻印《金罍山民手刻印存》四册",
    "date": {
      "year": 1911
    },
    "importance": 4,
    "tags": [
      "近代",
      "书法事件 / Calligraphy Event"
    ],
    "meta": {
      "dynasty": "近代",
      "traditionalDate": "宣统三年",
      "person": "徐三庚",
      "style": "书法事件 / Calligraphy Event",
      "sourceOrder": 1743
    },
    "creatorCn": "徐三庚",
    "imageUrl": "https://yishuwiki.oss-cn-beijing.aliyuncs.com/Operator/HistoricalEvent/2024/09/20240911160737842.png"
  },
  {
    "id": "66b4501e942c7eb28beebbba",
    "periodId": "modern_early",
    "streamId": "s_modern_early",
    "titleEn": "西泠印社辑黄易刻印成《秋景盦印谱》四册",
    "titleCn": "西泠印社辑黄易刻印成《秋景盦印谱》四册",
    "date": {
      "year": 1911
    },
    "importance": 4,
    "tags": [
      "近代",
      "篆刻与印学 / Seal Carving"
    ],
    "meta": {
      "dynasty": "近代",
      "traditionalDate": "宣统三年",
      "person": "黄易",
      "style": "篆刻与印学 / Seal Carving",
      "sourceOrder": 1744
    },
    "creatorCn": "黄易",
    "imageUrl": "https://yishuwiki.oss-cn-beijing.aliyuncs.com/Operator/HistoricalEvent/2024/09/20240911161440289.png",
    "descriptionCn": "《秋景盦印谱》另名《秋景庵主印谱》。"
  },
  {
    "id": "66b4501e942c7eb28beebbbb",
    "periodId": "modern_early",
    "streamId": "s_modern_early",
    "titleEn": "有正书局辑杨澥刻印成《杨龙石印存》二册",
    "titleCn": "有正书局辑杨澥刻印成《杨龙石印存》二册",
    "date": {
      "year": 1911
    },
    "importance": 4,
    "tags": [
      "近代",
      "书法事件 / Calligraphy Event"
    ],
    "meta": {
      "dynasty": "近代",
      "traditionalDate": "宣统三年",
      "person": "杨澥",
      "style": "书法事件 / Calligraphy Event",
      "sourceOrder": 1745
    },
    "creatorCn": "杨澥",
    "imageUrl": "https://yishuwiki.oss-cn-beijing.aliyuncs.com/Operator/HistoricalEvent/2024/09/20240911161812706.png"
  },
  {
    "id": "66b4501e942c7eb28beebbbc",
    "periodId": "modern_early",
    "streamId": "s_modern_early",
    "titleEn": "叶铭撰《广印人传》十七卷",
    "titleCn": "叶铭撰《广印人传》十七卷",
    "date": {
      "year": 1911
    },
    "importance": 4,
    "tags": [
      "近代",
      "书论与收藏 / Theory and Connoisseurship"
    ],
    "meta": {
      "dynasty": "近代",
      "traditionalDate": "宣统三年",
      "person": "叶铭",
      "style": "书论与收藏 / Theory and Connoisseurship",
      "sourceOrder": 1746
    },
    "creatorCn": "叶铭",
    "imageUrl": "https://yishuwiki.oss-cn-beijing.aliyuncs.com/Operator/HistoricalEvent/2024/09/20240911162036793.png"
  },
  {
    "id": "66b4501e942c7eb28beebbbd",
    "periodId": "modern_early",
    "streamId": "s_modern_early",
    "titleEn": "叶德辉撰《游艺卮言》",
    "titleCn": "叶德辉撰《游艺卮言》",
    "date": {
      "year": 1911
    },
    "importance": 4,
    "tags": [
      "近代",
      "书论与收藏 / Theory and Connoisseurship"
    ],
    "meta": {
      "dynasty": "近代",
      "traditionalDate": "宣统三年",
      "person": "叶德辉",
      "style": "书论与收藏 / Theory and Connoisseurship",
      "sourceOrder": 1747
    },
    "creatorCn": "叶德辉",
    "imageUrl": "https://yishuwiki.oss-cn-beijing.aliyuncs.com/Operator/HistoricalEvent/2024/09/20240911162323606.png"
  },
  {
    "id": "66b4501e942c7eb28beebbbe",
    "periodId": "modern_early",
    "streamId": "s_modern_early",
    "titleEn": "陕西西安出土汉《朝侯小子残碑》",
    "titleCn": "陕西西安出土汉《朝侯小子残碑》",
    "date": {
      "year": 1911
    },
    "importance": 4,
    "tags": [
      "近代",
      "楷书 / Regular Script"
    ],
    "meta": {
      "dynasty": "近代",
      "traditionalDate": "宣统三年",
      "person": "",
      "style": "楷书 / Regular Script",
      "sourceOrder": 1748
    },
    "imageUrl": "https://yishuwiki.oss-cn-beijing.aliyuncs.com/Operator/HistoricalEvent/2024/09/20240911162516177.png"
  },
  {
    "id": "66b4501e942c7eb28beebbbf",
    "periodId": "modern_early",
    "streamId": "s_modern_early",
    "titleEn": "齐白石书《扫地焚香》诗册",
    "titleCn": "齐白石书《扫地焚香》诗册",
    "date": {
      "year": 1912
    },
    "importance": 4,
    "tags": [
      "近代",
      "书法事件 / Calligraphy Event"
    ],
    "meta": {
      "dynasty": "近代",
      "traditionalDate": "民国元年",
      "person": "齐白石",
      "style": "书法事件 / Calligraphy Event",
      "sourceOrder": 1749
    },
    "creatorCn": "齐白石",
    "imageUrl": "https://yishuwiki.oss-cn-beijing.aliyuncs.com/Operator/HistoricalEvent/2024/09/20240911162628502.png"
  },
  {
    "id": "66b4501e942c7eb28beebbc0",
    "periodId": "modern_early",
    "streamId": "s_modern_early",
    "titleEn": "吴昌硕出任泠印社社长",
    "titleCn": "吴昌硕出任泠印社社长",
    "date": {
      "year": 1913
    },
    "importance": 4,
    "tags": [
      "近代",
      "书法事件 / Calligraphy Event"
    ],
    "meta": {
      "dynasty": "近代",
      "traditionalDate": "民国二年",
      "person": "吴昌硕",
      "style": "书法事件 / Calligraphy Event",
      "sourceOrder": 1750
    },
    "creatorCn": "吴昌硕",
    "imageUrl": "https://yishuwiki.oss-cn-beijing.aliyuncs.com/Operator/HistoricalEvent/2024/09/20240911162655120.png"
  },
  {
    "id": "66b4501e942c7eb28beebbc1",
    "periodId": "modern_early",
    "streamId": "s_modern_early",
    "titleEn": "金梁撰成《盛京故宫书画录》",
    "titleCn": "金梁撰成《盛京故宫书画录》",
    "date": {
      "year": 1913
    },
    "importance": 4,
    "tags": [
      "近代",
      "书论与收藏 / Theory and Connoisseurship"
    ],
    "meta": {
      "dynasty": "近代",
      "traditionalDate": "民国二年",
      "person": "金梁撰",
      "style": "书论与收藏 / Theory and Connoisseurship",
      "sourceOrder": 1751
    },
    "creatorCn": "金梁撰",
    "imageUrl": "https://yishuwiki.oss-cn-beijing.aliyuncs.com/Operator/HistoricalEvent/2024/09/20240911163016144.png"
  },
  {
    "id": "66b4501e942c7eb28beebbc2",
    "periodId": "modern_early",
    "streamId": "s_modern_early",
    "titleEn": "汪仁寿《金石大字典》出版",
    "titleCn": "汪仁寿《金石大字典》出版",
    "date": {
      "year": 1914
    },
    "importance": 4,
    "tags": [
      "近代",
      "书法事件 / Calligraphy Event"
    ],
    "meta": {
      "dynasty": "近代",
      "traditionalDate": "民国三年",
      "person": "汪仁寿",
      "style": "书法事件 / Calligraphy Event",
      "sourceOrder": 1752
    },
    "creatorCn": "汪仁寿",
    "imageUrl": "https://yishuwiki.oss-cn-beijing.aliyuncs.com/Operator/HistoricalEvent/2024/09/20240911163414932.png",
    "descriptionCn": "汪仁寿《金石大字典》由求古斋书局影印出版"
  },
  {
    "id": "66b4501e942c7eb28beebbc3",
    "periodId": "modern_early",
    "streamId": "s_modern_early",
    "titleEn": "罗振玉《殷虚书契考释》",
    "titleCn": "罗振玉《殷虚书契考释》",
    "date": {
      "year": 1915
    },
    "importance": 4,
    "tags": [
      "近代",
      "书法事件 / Calligraphy Event"
    ],
    "meta": {
      "dynasty": "近代",
      "traditionalDate": "民国四年",
      "person": "罗振玉",
      "style": "书法事件 / Calligraphy Event",
      "sourceOrder": 1753
    },
    "creatorCn": "罗振玉",
    "imageUrl": "https://yishuwiki.oss-cn-beijing.aliyuncs.com/Operator/HistoricalEvent/2024/09/20240911164238237.png"
  },
  {
    "id": "66b4501e942c7eb28beebbc4",
    "periodId": "modern_early",
    "streamId": "s_modern_early",
    "titleEn": "吴昌硕书《行书客来诗轴》",
    "titleCn": "吴昌硕书《行书客来诗轴》",
    "date": {
      "year": 1915
    },
    "importance": 4,
    "tags": [
      "近代",
      "行书 / Running Script"
    ],
    "meta": {
      "dynasty": "近代",
      "traditionalDate": "民国四年",
      "person": "吴昌硕",
      "style": "行书 / Running Script",
      "sourceOrder": 1754
    },
    "creatorCn": "吴昌硕",
    "imageUrl": "https://yishuwiki.oss-cn-beijing.aliyuncs.com/Operator/HistoricalEvent/2024/09/20240911164557124.png"
  },
  {
    "id": "66b4501e942c7eb28beebbc5",
    "periodId": "modern_early",
    "streamId": "s_modern_early",
    "titleEn": "罗振玉书《石鼓文考释》",
    "titleCn": "罗振玉书《石鼓文考释》",
    "date": {
      "year": 1916
    },
    "importance": 1,
    "tags": [
      "近代",
      "篆书 / Seal Script"
    ],
    "meta": {
      "dynasty": "近代",
      "traditionalDate": "民国五年",
      "person": "罗振玉",
      "style": "篆书 / Seal Script",
      "sourceOrder": 1755
    },
    "creatorCn": "罗振玉",
    "imageUrl": "https://yishuwiki.oss-cn-beijing.aliyuncs.com/Operator/HistoricalEvent/2024/09/20240911165152842.png"
  },
  {
    "id": "66b4501e942c7eb28beebbc6",
    "periodId": "modern_early",
    "streamId": "s_modern_early",
    "titleEn": "洛阳出土晋《张朗墓志》",
    "titleCn": "洛阳出土晋《张朗墓志》",
    "date": {
      "year": 1916
    },
    "importance": 4,
    "tags": [
      "近代",
      "楷书 / Regular Script"
    ],
    "meta": {
      "dynasty": "近代",
      "traditionalDate": "民国五年",
      "person": "",
      "style": "楷书 / Regular Script",
      "sourceOrder": 1756
    },
    "imageUrl": "https://yishuwiki.oss-cn-beijing.aliyuncs.com/Operator/HistoricalEvent/2024/09/20240911165412384.png"
  },
  {
    "id": "66b4501e942c7eb28beebbc7",
    "periodId": "modern_early",
    "streamId": "s_modern_early",
    "titleEn": "有正书局辑刊《历代古印大观》八册",
    "titleCn": "有正书局辑刊《历代古印大观》八册",
    "date": {
      "year": 1917
    },
    "importance": 4,
    "tags": [
      "近代",
      "书法事件 / Calligraphy Event"
    ],
    "meta": {
      "dynasty": "近代",
      "traditionalDate": "民国六年",
      "person": "",
      "style": "书法事件 / Calligraphy Event",
      "sourceOrder": 1757
    },
    "imageUrl": "https://yishuwiki.oss-cn-beijing.aliyuncs.com/Operator/HistoricalEvent/2024/09/20240911165745975.png"
  },
  {
    "id": "66b4501e942c7eb28beebbc8",
    "periodId": "modern_early",
    "streamId": "s_modern_early",
    "titleEn": "章士钊书《孙文诗轴》",
    "titleCn": "章士钊书《孙文诗轴》",
    "date": {
      "year": 1917
    },
    "importance": 4,
    "tags": [
      "近代",
      "书法事件 / Calligraphy Event"
    ],
    "meta": {
      "dynasty": "近代",
      "traditionalDate": "民国六年",
      "person": "章士钊",
      "style": "书法事件 / Calligraphy Event",
      "sourceOrder": 1758
    },
    "creatorCn": "章士钊",
    "imageUrl": "https://yishuwiki.oss-cn-beijing.aliyuncs.com/Operator/HistoricalEvent/2024/09/20240911165934257.png"
  },
  {
    "id": "66b4501e942c7eb28beebbc9",
    "periodId": "modern_early",
    "streamId": "s_modern_early",
    "titleEn": "杨逸书《遇石儗酒隶书七言联》",
    "titleCn": "杨逸书《遇石儗酒隶书七言联》",
    "date": {
      "year": 1917
    },
    "importance": 5,
    "tags": [
      "近代",
      "隶书与汉碑 / Clerical Script"
    ],
    "meta": {
      "dynasty": "近代",
      "traditionalDate": "民国六年",
      "person": "杨逸",
      "style": "隶书与汉碑 / Clerical Script",
      "sourceOrder": 1759
    },
    "creatorCn": "杨逸"
  },
  {
    "id": "66b4501e942c7eb28beebbca",
    "periodId": "modern_early",
    "streamId": "s_modern_early",
    "titleEn": "罗振玉书《临金文轴》",
    "titleCn": "罗振玉书《临金文轴》",
    "date": {
      "year": 1917
    },
    "importance": 4,
    "tags": [
      "近代",
      "金文 / Bronze Script"
    ],
    "meta": {
      "dynasty": "近代",
      "traditionalDate": "民国六年",
      "person": "罗振玉",
      "style": "金文 / Bronze Script",
      "sourceOrder": 1760
    },
    "creatorCn": "罗振玉",
    "imageUrl": "https://yishuwiki.oss-cn-beijing.aliyuncs.com/Operator/HistoricalEvent/2024/09/20240911170716152.png"
  },
  {
    "id": "66b4501f942c7eb28beebbcb",
    "periodId": "modern_early",
    "streamId": "s_modern_early",
    "titleEn": "吴大澂遗稿《愙斋集古录》印行",
    "titleCn": "吴大澂遗稿《愙斋集古录》印行",
    "date": {
      "year": 1917
    },
    "importance": 4,
    "tags": [
      "近代",
      "书法事件 / Calligraphy Event"
    ],
    "meta": {
      "dynasty": "近代",
      "traditionalDate": "民国六年",
      "person": "吴大澂",
      "style": "书法事件 / Calligraphy Event",
      "sourceOrder": 1761
    },
    "creatorCn": "吴大澂",
    "imageUrl": "https://yishuwiki.oss-cn-beijing.aliyuncs.com/Operator/HistoricalEvent/2024/09/20240911170845286.png"
  },
  {
    "id": "66b4501f942c7eb28beebbcc",
    "periodId": "modern_early",
    "streamId": "s_modern_early",
    "titleEn": "河南偃师出土晋《荀岳墓志》",
    "titleCn": "河南偃师出土晋《荀岳墓志》",
    "date": {
      "year": 1917
    },
    "importance": 4,
    "tags": [
      "近代",
      "楷书 / Regular Script"
    ],
    "meta": {
      "dynasty": "近代",
      "traditionalDate": "民国六年",
      "person": "",
      "style": "楷书 / Regular Script",
      "sourceOrder": 1762
    },
    "imageUrl": "https://yishuwiki.oss-cn-beijing.aliyuncs.com/Operator/HistoricalEvent/2024/09/20240911170942723.png"
  },
  {
    "id": "66b4501f942c7eb28beebbcd",
    "periodId": "modern_early",
    "streamId": "s_modern_early",
    "titleEn": "弘一法师书《格言横幅》",
    "titleCn": "弘一法师书《格言横幅》",
    "date": {
      "year": 1917
    },
    "importance": 4,
    "tags": [
      "近代",
      "书法事件 / Calligraphy Event"
    ],
    "meta": {
      "dynasty": "近代",
      "traditionalDate": "民国六年",
      "person": "弘一法师",
      "style": "书法事件 / Calligraphy Event",
      "sourceOrder": 1763
    },
    "creatorCn": "弘一法师",
    "imageUrl": "https://yishuwiki.oss-cn-beijing.aliyuncs.com/Operator/HistoricalEvent/2024/09/20240911171411768.png"
  },
  {
    "id": "66b4501f942c7eb28beebbce",
    "periodId": "modern_early",
    "streamId": "s_modern_early",
    "titleEn": "“千唐志斋”问世",
    "titleCn": "“千唐志斋”问世",
    "date": {
      "year": 1918
    },
    "importance": 4,
    "tags": [
      "近代",
      "书法事件 / Calligraphy Event"
    ],
    "meta": {
      "dynasty": "近代",
      "traditionalDate": "民国七年",
      "person": "张钫、章炳麟",
      "style": "书法事件 / Calligraphy Event",
      "sourceOrder": 1764
    },
    "creatorCn": "张钫、章炳麟",
    "imageUrl": "https://yishuwiki.oss-cn-beijing.aliyuncs.com/Operator/HistoricalEvent/2024/09/20240911171656111.png",
    "descriptionCn": "张钫搜集唐、宋、元、明、清志石于河南新安铁门镇，章炳麟为之命名，号“千唐志斋”。"
  },
  {
    "id": "66b4501f942c7eb28beebbcf",
    "periodId": "modern_early",
    "streamId": "s_modern_early",
    "titleEn": "罗振玉书《节临不簋盖铭文轴》",
    "titleCn": "罗振玉书《节临不簋盖铭文轴》",
    "date": {
      "year": 1918
    },
    "importance": 4,
    "tags": [
      "近代",
      "金文 / Bronze Script"
    ],
    "meta": {
      "dynasty": "近代",
      "traditionalDate": "民国七年",
      "person": "罗振玉",
      "style": "金文 / Bronze Script",
      "sourceOrder": 1765
    },
    "creatorCn": "罗振玉",
    "imageUrl": "https://yishuwiki.oss-cn-beijing.aliyuncs.com/Operator/HistoricalEvent/2024/09/20240911172034557.png"
  },
  {
    "id": "66b4501f942c7eb28beebbd0",
    "periodId": "modern_early",
    "streamId": "s_modern_early",
    "titleEn": "张宗祥撰《书学源流论》",
    "titleCn": "张宗祥撰《书学源流论》",
    "date": {
      "year": 1918
    },
    "importance": 4,
    "tags": [
      "近代",
      "书论与收藏 / Theory and Connoisseurship"
    ],
    "meta": {
      "dynasty": "近代",
      "traditionalDate": "民国七年",
      "person": "张宗祥",
      "style": "书论与收藏 / Theory and Connoisseurship",
      "sourceOrder": 1766
    },
    "creatorCn": "张宗祥",
    "imageUrl": "https://yishuwiki.oss-cn-beijing.aliyuncs.com/Operator/HistoricalEvent/2024/09/20240911172239029.png"
  },
  {
    "id": "66b4501f942c7eb28beebbd1",
    "periodId": "modern_early",
    "streamId": "s_modern_early",
    "titleEn": "弘一法师书《勇猛精进》横批",
    "titleCn": "弘一法师书《勇猛精进》横批",
    "date": {
      "year": 1918
    },
    "importance": 4,
    "tags": [
      "近代",
      "书法事件 / Calligraphy Event"
    ],
    "meta": {
      "dynasty": "近代",
      "traditionalDate": "民国七年",
      "person": "弘一法师",
      "style": "书法事件 / Calligraphy Event",
      "sourceOrder": 1767
    },
    "creatorCn": "弘一法师",
    "imageUrl": "https://yishuwiki.oss-cn-beijing.aliyuncs.com/Operator/HistoricalEvent/2024/09/20240911172929976.png"
  },
  {
    "id": "66b4501f942c7eb28beebbd2",
    "periodId": "modern_early",
    "streamId": "s_modern_early",
    "titleEn": "李叔同（弘一法师）书《李息翁临古法书》",
    "titleCn": "李叔同（弘一法师）书《李息翁临古法书》",
    "date": {
      "year": 1919
    },
    "importance": 4,
    "tags": [
      "近代",
      "书论与收藏 / Theory and Connoisseurship"
    ],
    "meta": {
      "dynasty": "近代",
      "traditionalDate": "民国八年",
      "person": "李叔同",
      "style": "书论与收藏 / Theory and Connoisseurship",
      "sourceOrder": 1768
    },
    "creatorCn": "李叔同",
    "imageUrl": "https://yishuwiki.oss-cn-beijing.aliyuncs.com/Operator/HistoricalEvent/2024/09/20240911173149923.png"
  },
  {
    "id": "66b4501f942c7eb28beebbd3",
    "periodId": "modern_early",
    "streamId": "s_modern_early",
    "titleEn": "吴隐编纂《遯盦印学丛书》",
    "titleCn": "吴隐编纂《遯盦印学丛书》",
    "date": {
      "year": 1920
    },
    "importance": 4,
    "tags": [
      "近代",
      "书法事件 / Calligraphy Event"
    ],
    "meta": {
      "dynasty": "近代",
      "traditionalDate": "民国九年",
      "person": "吴隐",
      "style": "书法事件 / Calligraphy Event",
      "sourceOrder": 1769
    },
    "creatorCn": "吴隐",
    "imageUrl": "https://yishuwiki.oss-cn-beijing.aliyuncs.com/Operator/HistoricalEvent/2024/09/20240911173345268.png",
    "descriptionCn": "吴隐编纂《遯盦印学丛书》十七卷（西泠印社版）。"
  },
  {
    "id": "66b4501f942c7eb28beebbd4",
    "periodId": "modern_early",
    "streamId": "s_modern_early",
    "titleEn": "洛阳出土北魏《元显墓志》",
    "titleCn": "洛阳出土北魏《元显墓志》",
    "date": {
      "year": 1920
    },
    "importance": 4,
    "tags": [
      "近代",
      "楷书 / Regular Script"
    ],
    "meta": {
      "dynasty": "近代",
      "traditionalDate": "民国九年",
      "person": "",
      "style": "楷书 / Regular Script",
      "sourceOrder": 1770
    },
    "imageUrl": "https://yishuwiki.oss-cn-beijing.aliyuncs.com/Operator/HistoricalEvent/2024/09/20240911173444396.png"
  },
  {
    "id": "66b4501f942c7eb28beebbd5",
    "periodId": "modern_early",
    "streamId": "s_modern_early",
    "titleEn": "王襄编《簠室殷契类纂》",
    "titleCn": "王襄编《簠室殷契类纂》",
    "date": {
      "year": 1920
    },
    "importance": 4,
    "tags": [
      "近代",
      "甲骨文 / Oracle-bone Script"
    ],
    "meta": {
      "dynasty": "近代",
      "traditionalDate": "民国九年",
      "person": "王襄",
      "style": "甲骨文 / Oracle-bone Script",
      "sourceOrder": 1771
    },
    "creatorCn": "王襄",
    "imageUrl": "https://yishuwiki.oss-cn-beijing.aliyuncs.com/Operator/HistoricalEvent/2024/09/20240911173741427.png",
    "descriptionCn": "王襄编《簠室殷契类纂》成，此为首部甲骨文字典。"
  },
  {
    "id": "66b4501f942c7eb28beebbd6",
    "periodId": "modern_early",
    "streamId": "s_modern_early",
    "titleEn": "李瑞清撰《玉梅庵论篆》",
    "titleCn": "李瑞清撰《玉梅庵论篆》",
    "date": {
      "year": 1920,
      "accuracy": "not_after"
    },
    "importance": 4,
    "tags": [
      "近代",
      "篆书 / Seal Script"
    ],
    "meta": {
      "dynasty": "近代",
      "traditionalDate": "民国九年以前",
      "person": "李瑞清",
      "style": "篆书 / Seal Script",
      "sourceOrder": 1772
    },
    "creatorCn": "李瑞清",
    "imageUrl": "https://yishuwiki.oss-cn-beijing.aliyuncs.com/Operator/HistoricalEvent/2024/09/20240911174243280.png"
  },
  {
    "id": "66b4501f942c7eb28beebbd7",
    "periodId": "modern_early",
    "streamId": "s_modern_early",
    "titleEn": "齐白石辑自刻印成《白石印草》",
    "titleCn": "齐白石辑自刻印成《白石印草》",
    "date": {
      "year": 1921
    },
    "importance": 4,
    "tags": [
      "近代",
      "书法事件 / Calligraphy Event"
    ],
    "meta": {
      "dynasty": "近代",
      "traditionalDate": "民国十年",
      "person": "齐白石",
      "style": "书法事件 / Calligraphy Event",
      "sourceOrder": 1773
    },
    "creatorCn": "齐白石",
    "imageUrl": "https://yishuwiki.oss-cn-beijing.aliyuncs.com/Operator/HistoricalEvent/2024/09/20240911174418658.png"
  },
  {
    "id": "66b4501f942c7eb28beebbd8",
    "periodId": "modern_early",
    "streamId": "s_modern_early",
    "titleEn": "曾熙书《致瘦碧仁兄行书轴》",
    "titleCn": "曾熙书《致瘦碧仁兄行书轴》",
    "date": {
      "year": 1921
    },
    "importance": 4,
    "tags": [
      "近代",
      "行书 / Running Script"
    ],
    "meta": {
      "dynasty": "近代",
      "traditionalDate": "民国十年",
      "person": "曾熙",
      "style": "行书 / Running Script",
      "sourceOrder": 1774
    },
    "creatorCn": "曾熙",
    "imageUrl": "https://yishuwiki.oss-cn-beijing.aliyuncs.com/Operator/HistoricalEvent/2024/09/20240911174736432.png"
  },
  {
    "id": "66b4501f942c7eb28beebbd9",
    "periodId": "modern_early",
    "streamId": "s_modern_early",
    "titleEn": "曾熙书《李文洁遗墨跋》",
    "titleCn": "曾熙书《李文洁遗墨跋》",
    "date": {
      "year": 1921
    },
    "importance": 4,
    "tags": [
      "近代",
      "书法事件 / Calligraphy Event"
    ],
    "meta": {
      "dynasty": "近代",
      "traditionalDate": "民国十年",
      "person": "曾熙",
      "style": "书法事件 / Calligraphy Event",
      "sourceOrder": 1775
    },
    "creatorCn": "曾熙",
    "imageUrl": "https://yishuwiki.oss-cn-beijing.aliyuncs.com/Operator/HistoricalEvent/2024/09/20240911175948818.png"
  },
  {
    "id": "66b4501f942c7eb28beebbda",
    "periodId": "modern_early",
    "streamId": "s_modern_early",
    "titleEn": "吴昌硕书《天帱高高篆书四言联》",
    "titleCn": "吴昌硕书《天帱高高篆书四言联》",
    "date": {
      "year": 1921
    },
    "importance": 4,
    "tags": [
      "近代",
      "篆书 / Seal Script"
    ],
    "meta": {
      "dynasty": "近代",
      "traditionalDate": "民国十年",
      "person": "吴昌硕",
      "style": "篆书 / Seal Script",
      "sourceOrder": 1776
    },
    "creatorCn": "吴昌硕",
    "imageUrl": "https://yishuwiki.oss-cn-beijing.aliyuncs.com/Operator/HistoricalEvent/2024/09/20240911180446121.png"
  },
  {
    "id": "66b4501f942c7eb28beebbdb",
    "periodId": "modern_early",
    "streamId": "s_modern_early",
    "titleEn": "沈曾植书《赠力农仁兄诗轴》",
    "titleCn": "沈曾植书《赠力农仁兄诗轴》",
    "date": {
      "year": 1922
    },
    "importance": 4,
    "tags": [
      "近代",
      "书法事件 / Calligraphy Event"
    ],
    "meta": {
      "dynasty": "近代",
      "traditionalDate": "民国十一年",
      "person": "沈曾植",
      "style": "书法事件 / Calligraphy Event",
      "sourceOrder": 1777
    },
    "creatorCn": "沈曾植",
    "imageUrl": "https://yishuwiki.oss-cn-beijing.aliyuncs.com/Operator/HistoricalEvent/2024/09/20240912093236205.png"
  },
  {
    "id": "66b4501f942c7eb28beebbdc",
    "periodId": "modern_early",
    "streamId": "s_modern_early",
    "titleEn": "吴昌硕书《豆新柳录大篆五言联》",
    "titleCn": "吴昌硕书《豆新柳录大篆五言联》",
    "date": {
      "year": 1922
    },
    "importance": 4,
    "tags": [
      "近代",
      "篆书 / Seal Script"
    ],
    "meta": {
      "dynasty": "近代",
      "traditionalDate": "民国十一年",
      "person": "吴昌硕",
      "style": "篆书 / Seal Script",
      "sourceOrder": 1778
    },
    "creatorCn": "吴昌硕",
    "imageUrl": "https://yishuwiki.oss-cn-beijing.aliyuncs.com/Operator/HistoricalEvent/2024/09/20240912093714240.png"
  },
  {
    "id": "66b4501f942c7eb28beebbdd",
    "periodId": "modern_early",
    "streamId": "s_modern_early",
    "titleEn": "弘一法师书《法常首座辞世词》",
    "titleCn": "弘一法师书《法常首座辞世词》",
    "date": {
      "year": 1922
    },
    "importance": 4,
    "tags": [
      "近代",
      "书法事件 / Calligraphy Event"
    ],
    "meta": {
      "dynasty": "近代",
      "traditionalDate": "民国十一年",
      "person": "弘一法师",
      "style": "书法事件 / Calligraphy Event",
      "sourceOrder": 1779
    },
    "creatorCn": "弘一法师",
    "imageUrl": "https://yishuwiki.oss-cn-beijing.aliyuncs.com/Operator/HistoricalEvent/2024/09/20240912094830888.png"
  },
  {
    "id": "66b4501f942c7eb28beebbde",
    "periodId": "modern_early",
    "streamId": "s_modern_early",
    "titleEn": "河南偃师出土汉《袁敞碑》",
    "titleCn": "河南偃师出土汉《袁敞碑》",
    "date": {
      "year": 1922
    },
    "importance": 4,
    "tags": [
      "近代",
      "楷书 / Regular Script"
    ],
    "meta": {
      "dynasty": "近代",
      "traditionalDate": "民国十一年",
      "person": "",
      "style": "楷书 / Regular Script",
      "sourceOrder": 1780
    },
    "imageUrl": "https://yishuwiki.oss-cn-beijing.aliyuncs.com/Operator/HistoricalEvent/2024/09/20240912095043816.png"
  },
  {
    "id": "66b4501f942c7eb28beebbdf",
    "periodId": "modern_early",
    "streamId": "s_modern_early",
    "titleEn": "洛阳出土汉《甘陵相尚府君碑》",
    "titleCn": "洛阳出土汉《甘陵相尚府君碑》",
    "date": {
      "year": 1922
    },
    "importance": 4,
    "tags": [
      "近代",
      "楷书 / Regular Script"
    ],
    "meta": {
      "dynasty": "近代",
      "traditionalDate": "民国十一年",
      "person": "",
      "style": "楷书 / Regular Script",
      "sourceOrder": 1781
    },
    "imageUrl": "https://yishuwiki.oss-cn-beijing.aliyuncs.com/Operator/HistoricalEvent/2024/09/20240912095309242.jpeg"
  },
  {
    "id": "66b4501f942c7eb28beebbe0",
    "periodId": "modern_early",
    "streamId": "s_modern_early",
    "titleEn": "洛阳出土三国魏《三体石经》残石",
    "titleCn": "洛阳出土三国魏《三体石经》残石",
    "date": {
      "year": 1922
    },
    "importance": 4,
    "tags": [
      "近代",
      "书法事件 / Calligraphy Event"
    ],
    "meta": {
      "dynasty": "近代",
      "traditionalDate": "民国十一年",
      "person": "",
      "style": "书法事件 / Calligraphy Event",
      "sourceOrder": 1782
    },
    "imageUrl": "https://yishuwiki.oss-cn-beijing.aliyuncs.com/Operator/HistoricalEvent/2024/09/20240912095346143.jpg"
  },
  {
    "id": "66b4501f942c7eb28beebbe1",
    "periodId": "modern_early",
    "streamId": "s_modern_early",
    "titleEn": "罗振玉辑《贞松堂唐宋以来官印集存》一册",
    "titleCn": "罗振玉辑《贞松堂唐宋以来官印集存》一册",
    "date": {
      "year": 1923
    },
    "importance": 4,
    "tags": [
      "近代",
      "书法事件 / Calligraphy Event"
    ],
    "meta": {
      "dynasty": "近代",
      "traditionalDate": "民国十二年",
      "person": "罗振玉",
      "style": "书法事件 / Calligraphy Event",
      "sourceOrder": 1783
    },
    "creatorCn": "罗振玉",
    "imageUrl": "https://yishuwiki.oss-cn-beijing.aliyuncs.com/Operator/HistoricalEvent/2024/11/20241126161401571.png"
  },
  {
    "id": "66b4501f942c7eb28beebbe2",
    "periodId": "modern_early",
    "streamId": "s_modern_early",
    "titleEn": "罗振玉书《为颐儿授室书联》",
    "titleCn": "罗振玉书《为颐儿授室书联》",
    "date": {
      "year": 1923
    },
    "importance": 4,
    "tags": [
      "近代",
      "书法事件 / Calligraphy Event"
    ],
    "meta": {
      "dynasty": "近代",
      "traditionalDate": "民国十二年",
      "person": "罗振玉",
      "style": "书法事件 / Calligraphy Event",
      "sourceOrder": 1784
    },
    "creatorCn": "罗振玉",
    "imageUrl": "https://yishuwiki.oss-cn-beijing.aliyuncs.com/Operator/HistoricalEvent/2024/09/20240912095759931.png"
  },
  {
    "id": "66b4501f942c7eb28beebbe3",
    "periodId": "modern_early",
    "streamId": "s_modern_early",
    "titleEn": "康有为书《听泉大字行书轴》",
    "titleCn": "康有为书《听泉大字行书轴》",
    "date": {
      "year": 1923
    },
    "importance": 1,
    "tags": [
      "近代",
      "行书 / Running Script"
    ],
    "meta": {
      "dynasty": "近代",
      "traditionalDate": "民国十二年",
      "person": "康有为",
      "style": "行书 / Running Script",
      "sourceOrder": 1785
    },
    "creatorCn": "康有为",
    "imageUrl": "https://yishuwiki.oss-cn-beijing.aliyuncs.com/Operator/HistoricalEvent/2024/09/20240912103214921.png"
  },
  {
    "id": "66b4501f942c7eb28beebbe4",
    "periodId": "modern_early",
    "streamId": "s_modern_early",
    "titleEn": "吴徵书《东坡题跋》行书轴",
    "titleCn": "吴徵书《东坡题跋》行书轴",
    "date": {
      "year": 1923
    },
    "importance": 4,
    "tags": [
      "近代",
      "行书 / Running Script"
    ],
    "meta": {
      "dynasty": "近代",
      "traditionalDate": "民国十二年",
      "person": "吴徵",
      "style": "行书 / Running Script",
      "sourceOrder": 1786
    },
    "creatorCn": "吴徵",
    "imageUrl": "https://yishuwiki.oss-cn-beijing.aliyuncs.com/Operator/HistoricalEvent/2024/09/20240912104159095.png"
  },
  {
    "id": "66b45020942c7eb28beebbe5",
    "periodId": "modern_early",
    "streamId": "s_modern_early",
    "titleEn": "齐白石书《赠胡生鄂公序》",
    "titleCn": "齐白石书《赠胡生鄂公序》",
    "date": {
      "year": 1924
    },
    "importance": 4,
    "tags": [
      "近代",
      "书法事件 / Calligraphy Event"
    ],
    "meta": {
      "dynasty": "近代",
      "traditionalDate": "民国十三年",
      "person": "齐白石",
      "style": "书法事件 / Calligraphy Event",
      "sourceOrder": 1787
    },
    "creatorCn": "齐白石",
    "imageUrl": "https://yishuwiki.oss-cn-beijing.aliyuncs.com/Operator/HistoricalEvent/2024/09/20240912104827443.png"
  },
  {
    "id": "66b45020942c7eb28beebbe6",
    "periodId": "modern_early",
    "streamId": "s_modern_early",
    "titleEn": "吴昌硕书《篆书临石鼓文》",
    "titleCn": "吴昌硕书《篆书临石鼓文》",
    "date": {
      "year": 1925
    },
    "importance": 1,
    "tags": [
      "近代",
      "篆书 / Seal Script"
    ],
    "meta": {
      "dynasty": "近代",
      "traditionalDate": "民国十三年",
      "person": "吴昌硕",
      "style": "篆书 / Seal Script",
      "sourceOrder": 1788
    },
    "creatorCn": "吴昌硕",
    "imageUrl": "https://yishuwiki.oss-cn-beijing.aliyuncs.com/Operator/HistoricalEvent/2024/09/20240912110158350.png"
  },
  {
    "id": "66b45020942c7eb28beebbe7",
    "periodId": "modern_early",
    "streamId": "s_modern_early",
    "titleEn": "容庚《金文编》出版",
    "titleCn": "容庚《金文编》出版",
    "date": {
      "year": 1925
    },
    "importance": 4,
    "tags": [
      "近代",
      "金文 / Bronze Script"
    ],
    "meta": {
      "dynasty": "近代",
      "traditionalDate": "民国十三年",
      "person": "容庚",
      "style": "金文 / Bronze Script",
      "sourceOrder": 1789
    },
    "creatorCn": "容庚",
    "imageUrl": "https://yishuwiki.oss-cn-beijing.aliyuncs.com/Operator/HistoricalEvent/2024/11/20241126161519776.png",
    "descriptionCn": "贻安堂出版容庚《金文编》"
  },
  {
    "id": "66b45020942c7eb28beebbe8",
    "periodId": "modern_early",
    "streamId": "s_modern_early",
    "titleEn": "陈和祥《四体大字典》出版",
    "titleCn": "陈和祥《四体大字典》出版",
    "date": {
      "year": 1925
    },
    "importance": 4,
    "tags": [
      "近代",
      "书法事件 / Calligraphy Event"
    ],
    "meta": {
      "dynasty": "近代",
      "traditionalDate": "民国十三年",
      "person": "陈和祥",
      "style": "书法事件 / Calligraphy Event",
      "sourceOrder": 1790
    },
    "creatorCn": "陈和祥",
    "imageUrl": "https://yishuwiki.oss-cn-beijing.aliyuncs.com/Operator/HistoricalEvent/2024/09/20240912110758821.png",
    "descriptionCn": "扫叶山房影印出版陈和祥《四体大字典》"
  },
  {
    "id": "66b45020942c7eb28beebbe9",
    "periodId": "modern_early",
    "streamId": "s_modern_early",
    "titleEn": "谢无量书《赠元直仁兄扇面》",
    "titleCn": "谢无量书《赠元直仁兄扇面》",
    "date": {
      "year": 1925
    },
    "importance": 4,
    "tags": [
      "近代",
      "书法事件 / Calligraphy Event"
    ],
    "meta": {
      "dynasty": "近代",
      "traditionalDate": "民国十三年",
      "person": "谢无量",
      "style": "书法事件 / Calligraphy Event",
      "sourceOrder": 1791
    },
    "creatorCn": "谢无量",
    "imageUrl": "https://yishuwiki.oss-cn-beijing.aliyuncs.com/Operator/HistoricalEvent/2024/09/20240912111053108.png"
  },
  {
    "id": "66b45020942c7eb28beebbea",
    "periodId": "modern_early",
    "streamId": "s_modern_early",
    "titleEn": "古物保存所编纂历代内府所藏为《内务部古物陈列所书画目录》一卷",
    "titleCn": "古物保存所编纂历代内府所藏为《内务部古物陈列所书画目录》一卷",
    "date": {
      "year": 1925
    },
    "importance": 4,
    "tags": [
      "近代",
      "书法事件 / Calligraphy Event"
    ],
    "meta": {
      "dynasty": "近代",
      "traditionalDate": "民国十三年",
      "person": "",
      "style": "书法事件 / Calligraphy Event",
      "sourceOrder": 1792
    },
    "imageUrl": "https://yishuwiki.oss-cn-beijing.aliyuncs.com/Operator/HistoricalEvent/2024/09/20240912111619113.png"
  },
  {
    "id": "66b45020942c7eb28beebbeb",
    "periodId": "modern_early",
    "streamId": "s_modern_early",
    "titleEn": "梁启超书《隶书八言联》",
    "titleCn": "梁启超书《隶书八言联》",
    "date": {
      "year": 1925
    },
    "importance": 4,
    "tags": [
      "近代",
      "隶书与汉碑 / Clerical Script"
    ],
    "meta": {
      "dynasty": "近代",
      "traditionalDate": "民国十三年",
      "person": "梁启超",
      "style": "隶书与汉碑 / Clerical Script",
      "sourceOrder": 1793
    },
    "creatorCn": "梁启超",
    "imageUrl": "https://yishuwiki.oss-cn-beijing.aliyuncs.com/Operator/HistoricalEvent/2024/11/20241126161314289.png"
  },
  {
    "id": "66b45020942c7eb28beebbec",
    "periodId": "modern_early",
    "streamId": "s_modern_early",
    "titleEn": "章太严书《赠鸥篆书联》",
    "titleCn": "章太严书《赠鸥篆书联》",
    "date": {
      "year": 1926
    },
    "importance": 4,
    "tags": [
      "近代",
      "篆书 / Seal Script"
    ],
    "meta": {
      "dynasty": "近代",
      "traditionalDate": "民国十五年",
      "person": "章太严",
      "style": "篆书 / Seal Script",
      "sourceOrder": 1794
    },
    "creatorCn": "章太严",
    "imageUrl": "https://yishuwiki.oss-cn-beijing.aliyuncs.com/Operator/HistoricalEvent/2024/09/20240912111847543.png"
  },
  {
    "id": "66b45020942c7eb28beebbed",
    "periodId": "modern_early",
    "streamId": "s_modern_early",
    "titleEn": "中国西北科学考察团发现木杆“居延笔”",
    "titleCn": "中国西北科学考察团发现木杆“居延笔”",
    "date": {
      "year": 1927
    },
    "importance": 4,
    "tags": [
      "近代",
      "书法事件 / Calligraphy Event"
    ],
    "meta": {
      "dynasty": "近代",
      "traditionalDate": "民国十六年",
      "person": "",
      "style": "书法事件 / Calligraphy Event",
      "sourceOrder": 1795
    },
    "imageUrl": "https://yishuwiki.oss-cn-beijing.aliyuncs.com/Operator/HistoricalEvent/2024/09/20240912112154127.png",
    "descriptionCn": "中国西北科学考察团于内蒙额济纳河汉代烽隧遗址发现木杆“居延笔”"
  },
  {
    "id": "66b45020942c7eb28beebbee",
    "periodId": "modern_early",
    "streamId": "s_modern_early",
    "titleEn": "于右任书《总理遗嘱》楷书轴",
    "titleCn": "于右任书《总理遗嘱》楷书轴",
    "date": {
      "year": 1927
    },
    "importance": 4,
    "tags": [
      "近代",
      "楷书 / Regular Script"
    ],
    "meta": {
      "dynasty": "近代",
      "traditionalDate": "民国十六年",
      "person": "于右任",
      "style": "楷书 / Regular Script",
      "sourceOrder": 1796
    },
    "creatorCn": "于右任",
    "imageUrl": "https://yishuwiki.oss-cn-beijing.aliyuncs.com/Operator/HistoricalEvent/2024/09/20240912112441463.png"
  },
  {
    "id": "66b45020942c7eb28beebbef",
    "periodId": "modern_early",
    "streamId": "s_modern_early",
    "titleEn": "方介堪辑自刻印成《方介堪印谱》二册",
    "titleCn": "方介堪辑自刻印成《方介堪印谱》二册",
    "date": {
      "year": 1927
    },
    "importance": 4,
    "tags": [
      "近代",
      "篆刻与印学 / Seal Carving"
    ],
    "meta": {
      "dynasty": "近代",
      "traditionalDate": "民国十六年",
      "person": "方介堪",
      "style": "篆刻与印学 / Seal Carving",
      "sourceOrder": 1797
    },
    "creatorCn": "方介堪",
    "imageUrl": "https://yishuwiki.oss-cn-beijing.aliyuncs.com/Operator/HistoricalEvent/2024/09/20240912113158880.png"
  },
  {
    "id": "66b45020942c7eb28beebbf2",
    "periodId": "modern_early",
    "streamId": "s_modern_early",
    "titleEn": "河南偃师发现汉《袁安碑》",
    "titleCn": "河南偃师发现汉《袁安碑》",
    "date": {
      "year": 1927
    },
    "importance": 2,
    "tags": [
      "近代",
      "楷书 / Regular Script"
    ],
    "meta": {
      "dynasty": "近代",
      "traditionalDate": "民国十六年",
      "person": "",
      "style": "楷书 / Regular Script",
      "sourceOrder": 1800
    },
    "imageUrl": "https://yishuwiki.oss-cn-beijing.aliyuncs.com/Operator/HistoricalEvent/2024/09/20240912113747002.png"
  },
  {
    "id": "66b45020942c7eb28beebbf3",
    "periodId": "modern_early",
    "streamId": "s_modern_early",
    "titleEn": "罗福颐编纂《汉印文字征》",
    "titleCn": "罗福颐编纂《汉印文字征》",
    "date": {
      "year": 1927
    },
    "importance": 4,
    "tags": [
      "近代",
      "书法事件 / Calligraphy Event"
    ],
    "meta": {
      "dynasty": "近代",
      "traditionalDate": "民国十六年",
      "person": "罗福颐",
      "style": "书法事件 / Calligraphy Event",
      "sourceOrder": 1801
    },
    "creatorCn": "罗福颐",
    "imageUrl": "https://yishuwiki.oss-cn-beijing.aliyuncs.com/Operator/HistoricalEvent/2024/09/20240912114319230.png"
  },
  {
    "id": "66b45020942c7eb28beebbf4",
    "periodId": "modern_early",
    "streamId": "s_modern_early",
    "titleEn": "卓定谋著《章草考》",
    "titleCn": "卓定谋著《章草考》",
    "date": {
      "year": 1927
    },
    "importance": 4,
    "tags": [
      "近代",
      "书论与收藏 / Theory and Connoisseurship"
    ],
    "meta": {
      "dynasty": "近代",
      "traditionalDate": "民国十六年",
      "person": "卓定谋",
      "style": "书论与收藏 / Theory and Connoisseurship",
      "sourceOrder": 1802
    },
    "creatorCn": "卓定谋",
    "imageUrl": "https://yishuwiki.oss-cn-beijing.aliyuncs.com/Operator/HistoricalEvent/2024/11/20241126164851094.png"
  },
  {
    "id": "66b45020942c7eb28beebbf7",
    "periodId": "modern_early",
    "streamId": "s_modern_early",
    "titleEn": "马公愚辑《公愚印谱》",
    "titleCn": "马公愚辑《公愚印谱》",
    "date": {
      "year": 1927
    },
    "importance": 4,
    "tags": [
      "近代",
      "篆刻与印学 / Seal Carving"
    ],
    "meta": {
      "dynasty": "近代",
      "traditionalDate": "民国十六年",
      "person": "马公愚",
      "style": "篆刻与印学 / Seal Carving",
      "sourceOrder": 1805
    },
    "creatorCn": "马公愚",
    "imageUrl": "https://yishuwiki.oss-cn-beijing.aliyuncs.com/Operator/HistoricalEvent/2024/09/20240912122142351.png"
  },
  {
    "id": "66b45020942c7eb28beebbf0",
    "periodId": "modern_early",
    "streamId": "s_modern_early",
    "titleEn": "《画史汇稿文征明》刊行",
    "titleCn": "《画史汇稿文征明》刊行",
    "date": {
      "year": 1929
    },
    "importance": 4,
    "tags": [
      "近代",
      "书法事件 / Calligraphy Event"
    ],
    "meta": {
      "dynasty": "近代",
      "traditionalDate": "民国十八年",
      "person": "",
      "style": "书法事件 / Calligraphy Event",
      "sourceOrder": 1798
    },
    "imageUrl": "https://yishuwiki.oss-cn-beijing.aliyuncs.com/Operator/HistoricalEvent/2024/09/20240912113526039.png"
  },
  {
    "id": "66b45020942c7eb28beebbf1",
    "periodId": "modern_early",
    "streamId": "s_modern_early",
    "titleEn": "曾熙书《致春渠先先生大篆轴》",
    "titleCn": "曾熙书《致春渠先先生大篆轴》",
    "date": {
      "year": 1929
    },
    "importance": 4,
    "tags": [
      "近代",
      "篆书 / Seal Script"
    ],
    "meta": {
      "dynasty": "近代",
      "traditionalDate": "民国十八年",
      "person": "曾熙",
      "style": "篆书 / Seal Script",
      "sourceOrder": 1799
    },
    "creatorCn": "曾熙",
    "imageUrl": "https://yishuwiki.oss-cn-beijing.aliyuncs.com/Operator/HistoricalEvent/2024/09/20240912113726257.png"
  },
  {
    "id": "66b45020942c7eb28beebbf5",
    "periodId": "modern_early",
    "streamId": "s_modern_early",
    "titleEn": "中国西北科学考查团发掘汉简",
    "titleCn": "中国西北科学考查团发掘汉简",
    "date": {
      "year": 1930
    },
    "importance": 4,
    "tags": [
      "近代",
      "书法事件 / Calligraphy Event"
    ],
    "meta": {
      "dynasty": "近代",
      "traditionalDate": "民国十九年",
      "person": "",
      "style": "书法事件 / Calligraphy Event",
      "sourceOrder": 1803
    },
    "imageUrl": "https://yishuwiki.oss-cn-beijing.aliyuncs.com/Operator/HistoricalEvent/2024/09/20240912115253302.png",
    "descriptionCn": "中国西北科学考查团在内蒙额济纳河流域汉代烽隧遗址发掘汉简一万余枚"
  },
  {
    "id": "66b45020942c7eb28beebbf6",
    "periodId": "modern_early",
    "streamId": "s_modern_early",
    "titleEn": "黄文弼得汉简",
    "titleCn": "黄文弼得汉简",
    "date": {
      "year": 1930
    },
    "importance": 4,
    "tags": [
      "近代",
      "书法事件 / Calligraphy Event"
    ],
    "meta": {
      "dynasty": "近代",
      "traditionalDate": "民国十九年",
      "person": "黄文弼",
      "style": "书法事件 / Calligraphy Event",
      "sourceOrder": 1804
    },
    "creatorCn": "黄文弼",
    "imageUrl": "https://yishuwiki.oss-cn-beijing.aliyuncs.com/Operator/HistoricalEvent/2024/09/20240912115858386.png",
    "descriptionCn": "黄文弼于新疆得汉简七十余枚"
  },
  {
    "id": "66b45020942c7eb28beebbf8",
    "periodId": "modern_early",
    "streamId": "s_modern_early",
    "titleEn": "曾熙书《倚竹乐驎楷书六言联》",
    "titleCn": "曾熙书《倚竹乐驎楷书六言联》",
    "date": {
      "year": 1930,
      "accuracy": "not_after"
    },
    "importance": 4,
    "tags": [
      "近代",
      "楷书 / Regular Script"
    ],
    "meta": {
      "dynasty": "近代",
      "traditionalDate": "民国十九年以前",
      "person": "曾熙",
      "style": "楷书 / Regular Script",
      "sourceOrder": 1806
    },
    "creatorCn": "曾熙",
    "imageUrl": "https://yishuwiki.oss-cn-beijing.aliyuncs.com/Operator/HistoricalEvent/2024/09/20240912122410319.png"
  },
  {
    "id": "66b45020942c7eb28beebbf9",
    "periodId": "modern_early",
    "streamId": "s_modern_early",
    "titleEn": "曾熙书《天亦惜斯文行书五言诗》",
    "titleCn": "曾熙书《天亦惜斯文行书五言诗》",
    "date": {
      "year": 1930,
      "accuracy": "not_after"
    },
    "importance": 4,
    "tags": [
      "近代",
      "行书 / Running Script"
    ],
    "meta": {
      "dynasty": "近代",
      "traditionalDate": "民国十九年以前",
      "person": "曾熙",
      "style": "行书 / Running Script",
      "sourceOrder": 1807
    },
    "creatorCn": "曾熙",
    "imageUrl": "https://yishuwiki.oss-cn-beijing.aliyuncs.com/Operator/HistoricalEvent/2024/09/20240912122844381.png"
  },
  {
    "id": "66b45020942c7eb28beebbfa",
    "periodId": "modern_early",
    "streamId": "s_modern_early",
    "titleEn": "余绍宋撰《书画书录解题》",
    "titleCn": "余绍宋撰《书画书录解题》",
    "date": {
      "year": 1931
    },
    "importance": 4,
    "tags": [
      "近代",
      "书论与收藏 / Theory and Connoisseurship"
    ],
    "meta": {
      "dynasty": "近代",
      "traditionalDate": "民国二十年",
      "person": "余绍宋",
      "style": "书论与收藏 / Theory and Connoisseurship",
      "sourceOrder": 1808
    },
    "creatorCn": "余绍宋",
    "imageUrl": "https://yishuwiki.oss-cn-beijing.aliyuncs.com/Operator/HistoricalEvent/2024/09/20240912140558367.png"
  },
  {
    "id": "66b45020942c7eb28beebbfb",
    "periodId": "modern_early",
    "streamId": "s_modern_early",
    "titleEn": "王福庵书《节庚子山春赋篆书轴》",
    "titleCn": "王福庵书《节庚子山春赋篆书轴》",
    "date": {
      "year": 1931
    },
    "importance": 4,
    "tags": [
      "近代",
      "篆书 / Seal Script"
    ],
    "meta": {
      "dynasty": "近代",
      "traditionalDate": "民国二十年",
      "person": "王福庵",
      "style": "篆书 / Seal Script",
      "sourceOrder": 1809
    },
    "creatorCn": "王福庵",
    "imageUrl": "https://yishuwiki.oss-cn-beijing.aliyuncs.com/Operator/HistoricalEvent/2024/09/20240912142255548.png"
  },
  {
    "id": "66b45020942c7eb28beebbfc",
    "periodId": "modern_early",
    "streamId": "s_modern_early",
    "titleEn": "罗福颐撰《印谱考》四卷",
    "titleCn": "罗福颐撰《印谱考》四卷",
    "date": {
      "year": 1931
    },
    "importance": 4,
    "tags": [
      "近代",
      "篆刻与印学 / Seal Carving"
    ],
    "meta": {
      "dynasty": "近代",
      "traditionalDate": "民国二十年",
      "person": "罗福颐",
      "style": "篆刻与印学 / Seal Carving",
      "sourceOrder": 1810
    },
    "creatorCn": "罗福颐",
    "imageUrl": "https://yishuwiki.oss-cn-beijing.aliyuncs.com/Operator/HistoricalEvent/2024/09/20240912143731957.png"
  },
  {
    "id": "66b45020942c7eb28beebbfd",
    "periodId": "modern_early",
    "streamId": "s_modern_early",
    "titleEn": "张大千书《壬辰岁书轴》",
    "titleCn": "张大千书《壬辰岁书轴》",
    "date": {
      "year": 1931
    },
    "importance": 4,
    "tags": [
      "近代",
      "书法事件 / Calligraphy Event"
    ],
    "meta": {
      "dynasty": "近代",
      "traditionalDate": "民国二十年",
      "person": "张大千",
      "style": "书法事件 / Calligraphy Event",
      "sourceOrder": 1811
    },
    "creatorCn": "张大千",
    "imageUrl": "https://yishuwiki.oss-cn-beijing.aliyuncs.com/Operator/HistoricalEvent/2024/09/20240912144213952.png"
  },
  {
    "id": "66b45020942c7eb28beebbfe",
    "periodId": "modern_early",
    "streamId": "s_modern_early",
    "titleEn": "容庚书《为顾颉刚题联》",
    "titleCn": "容庚书《为顾颉刚题联》",
    "date": {
      "year": 1932
    },
    "importance": 4,
    "tags": [
      "近代",
      "书法事件 / Calligraphy Event"
    ],
    "meta": {
      "dynasty": "近代",
      "traditionalDate": "民国二十一年",
      "person": "容庚",
      "style": "书法事件 / Calligraphy Event",
      "sourceOrder": 1812
    },
    "creatorCn": "容庚",
    "imageUrl": "https://yishuwiki.oss-cn-beijing.aliyuncs.com/Operator/HistoricalEvent/2024/09/20240912144818943.png"
  },
  {
    "id": "66b45020942c7eb28beebbff",
    "periodId": "modern_early",
    "streamId": "s_modern_early",
    "titleEn": "郭沫若撰《两周金文辞大系图录考释》印行",
    "titleCn": "郭沫若撰《两周金文辞大系图录考释》印行",
    "date": {
      "year": 1932
    },
    "importance": 4,
    "tags": [
      "近代",
      "金文 / Bronze Script"
    ],
    "meta": {
      "dynasty": "近代",
      "traditionalDate": "民国二十一年",
      "person": "郭沫若",
      "style": "金文 / Bronze Script",
      "sourceOrder": 1813
    },
    "creatorCn": "郭沫若",
    "imageUrl": "https://yishuwiki.oss-cn-beijing.aliyuncs.com/Operator/HistoricalEvent/2024/11/20241126155906598.png"
  },
  {
    "id": "66b45020942c7eb28beebc00",
    "periodId": "modern_early",
    "streamId": "s_modern_early",
    "titleEn": "胡小石书《临流沙坠简屏》",
    "titleCn": "胡小石书《临流沙坠简屏》",
    "date": {
      "year": 1932
    },
    "importance": 4,
    "tags": [
      "近代",
      "书法事件 / Calligraphy Event"
    ],
    "meta": {
      "dynasty": "近代",
      "traditionalDate": "民国二十一年",
      "person": "胡小石",
      "style": "书法事件 / Calligraphy Event",
      "sourceOrder": 1814
    },
    "creatorCn": "胡小石",
    "imageUrl": "https://yishuwiki.oss-cn-beijing.aliyuncs.com/Operator/HistoricalEvent/2024/09/20240912145314093.png"
  },
  {
    "id": "66b45021942c7eb28beebc01",
    "periodId": "modern_early",
    "streamId": "s_modern_early",
    "titleEn": "青海乐都出土汉《三老椽赵宽碑》",
    "titleCn": "青海乐都出土汉《三老椽赵宽碑》",
    "date": {
      "year": 1933
    },
    "importance": 4,
    "tags": [
      "近代",
      "楷书 / Regular Script"
    ],
    "meta": {
      "dynasty": "近代",
      "traditionalDate": "民国二十二年",
      "person": "",
      "style": "楷书 / Regular Script",
      "sourceOrder": 1815
    },
    "imageUrl": "https://yishuwiki.oss-cn-beijing.aliyuncs.com/Operator/HistoricalEvent/2024/09/20240912145451392.png"
  },
  {
    "id": "66b45021942c7eb28beebc02",
    "periodId": "modern_early",
    "streamId": "s_modern_early",
    "titleEn": "弘一法师书《心经条屏》",
    "titleCn": "弘一法师书《心经条屏》",
    "date": {
      "year": 1933
    },
    "importance": 4,
    "tags": [
      "近代",
      "书法事件 / Calligraphy Event"
    ],
    "meta": {
      "dynasty": "近代",
      "traditionalDate": "民国二十二年",
      "person": "弘一法师",
      "style": "书法事件 / Calligraphy Event",
      "sourceOrder": 1816
    },
    "creatorCn": "弘一法师",
    "imageUrl": "https://yishuwiki.oss-cn-beijing.aliyuncs.com/Operator/HistoricalEvent/2024/09/20240912152402193.png"
  },
  {
    "id": "66b45021942c7eb28beebc03",
    "periodId": "modern_early",
    "streamId": "s_modern_early",
    "titleEn": "马宗霍著《书林藻鉴》",
    "titleCn": "马宗霍著《书林藻鉴》",
    "date": {
      "year": 1934
    },
    "importance": 4,
    "tags": [
      "近代",
      "书论与收藏 / Theory and Connoisseurship"
    ],
    "meta": {
      "dynasty": "近代",
      "traditionalDate": "民国二十三年",
      "person": "马宗霍",
      "style": "书论与收藏 / Theory and Connoisseurship",
      "sourceOrder": 1817
    },
    "creatorCn": "马宗霍",
    "imageUrl": "https://yishuwiki.oss-cn-beijing.aliyuncs.com/Operator/HistoricalEvent/2024/09/20240912152808589.png"
  },
  {
    "id": "66b45021942c7eb28beebc04",
    "periodId": "modern_early",
    "streamId": "s_modern_early",
    "titleEn": "齐白石书《赠冷厂画友先生词轴》",
    "titleCn": "齐白石书《赠冷厂画友先生词轴》",
    "date": {
      "year": 1934
    },
    "importance": 4,
    "tags": [
      "近代",
      "书法事件 / Calligraphy Event"
    ],
    "meta": {
      "dynasty": "近代",
      "traditionalDate": "民国二十三年",
      "person": "齐白石",
      "style": "书法事件 / Calligraphy Event",
      "sourceOrder": 1818
    },
    "creatorCn": "齐白石",
    "imageUrl": "https://yishuwiki.oss-cn-beijing.aliyuncs.com/Operator/HistoricalEvent/2024/09/20240912153428933.png"
  },
  {
    "id": "66b45021942c7eb28beebc05",
    "periodId": "modern_early",
    "streamId": "s_modern_early",
    "titleEn": "孙海波《甲骨文编》完成",
    "titleCn": "孙海波《甲骨文编》完成",
    "date": {
      "year": 1934
    },
    "importance": 1,
    "tags": [
      "近代",
      "甲骨文 / Oracle-bone Script"
    ],
    "meta": {
      "dynasty": "近代",
      "traditionalDate": "民国二十三年",
      "person": "孙海波",
      "style": "甲骨文 / Oracle-bone Script",
      "sourceOrder": 1819
    },
    "creatorCn": "孙海波",
    "imageUrl": "https://yishuwiki.oss-cn-beijing.aliyuncs.com/Operator/HistoricalEvent/2024/09/20240912153636396.png"
  },
  {
    "id": "66b45021942c7eb28beebc06",
    "periodId": "modern_early",
    "streamId": "s_modern_early",
    "titleEn": "西泠印社辑《现代篆刻》一至九集",
    "titleCn": "西泠印社辑《现代篆刻》一至九集",
    "date": {
      "year": 1934
    },
    "importance": 4,
    "tags": [
      "近代",
      "篆书 / Seal Script"
    ],
    "meta": {
      "dynasty": "近代",
      "traditionalDate": "民国二十三年",
      "person": "",
      "style": "篆书 / Seal Script",
      "sourceOrder": 1820
    },
    "imageUrl": "https://yishuwiki.oss-cn-beijing.aliyuncs.com/Operator/HistoricalEvent/2024/11/20241126164452793.png"
  },
  {
    "id": "66b45021942c7eb28beebc07",
    "periodId": "modern_early",
    "streamId": "s_modern_early",
    "titleEn": "文成郁《书法辑要》刊行",
    "titleCn": "文成郁《书法辑要》刊行",
    "date": {
      "year": 1934
    },
    "importance": 4,
    "tags": [
      "近代",
      "书法事件 / Calligraphy Event"
    ],
    "meta": {
      "dynasty": "近代",
      "traditionalDate": "民国二十三年",
      "person": "文成郁",
      "style": "书法事件 / Calligraphy Event",
      "sourceOrder": 1821
    },
    "creatorCn": "文成郁",
    "imageUrl": "https://yishuwiki.oss-cn-beijing.aliyuncs.com/Operator/HistoricalEvent/2024/09/20240912154241859.png"
  },
  {
    "id": "66b45021942c7eb28beebc08",
    "periodId": "modern_early",
    "streamId": "s_modern_early",
    "titleEn": "罗振玉编纂《三代吉金文存》",
    "titleCn": "罗振玉编纂《三代吉金文存》",
    "date": {
      "year": 1935
    },
    "importance": 4,
    "tags": [
      "近代",
      "金文 / Bronze Script"
    ],
    "meta": {
      "dynasty": "近代",
      "traditionalDate": "民国二十四年",
      "person": "罗振玉",
      "style": "金文 / Bronze Script",
      "sourceOrder": 1822
    },
    "creatorCn": "罗振玉",
    "imageUrl": "https://yishuwiki.oss-cn-beijing.aliyuncs.com/Operator/HistoricalEvent/2024/11/20241126161342424.png",
    "descriptionCn": "罗振玉编纂《三代吉金文存》二十卷，翌年书成。"
  },
  {
    "id": "66b45021942c7eb28beebc09",
    "periodId": "modern_early",
    "streamId": "s_modern_early",
    "titleEn": "邓尔雅书《乙亥冬日楷书扇面》",
    "titleCn": "邓尔雅书《乙亥冬日楷书扇面》",
    "date": {
      "year": 1935
    },
    "importance": 4,
    "tags": [
      "近代",
      "楷书 / Regular Script"
    ],
    "meta": {
      "dynasty": "近代",
      "traditionalDate": "民国二十四年",
      "person": "邓尔雅",
      "style": "楷书 / Regular Script",
      "sourceOrder": 1823
    },
    "creatorCn": "邓尔雅",
    "imageUrl": "https://yishuwiki.oss-cn-beijing.aliyuncs.com/Operator/HistoricalEvent/2024/09/20240912155352271.png"
  },
  {
    "id": "66b45021942c7eb28beebc0a",
    "periodId": "modern_early",
    "streamId": "s_modern_early",
    "titleEn": "马宗霍著《书林纪事》",
    "titleCn": "马宗霍著《书林纪事》",
    "date": {
      "year": 1935
    },
    "importance": 4,
    "tags": [
      "近代",
      "书论与收藏 / Theory and Connoisseurship"
    ],
    "meta": {
      "dynasty": "近代",
      "traditionalDate": "民国二十四年",
      "person": "马宗霍",
      "style": "书论与收藏 / Theory and Connoisseurship",
      "sourceOrder": 1824
    },
    "creatorCn": "马宗霍",
    "imageUrl": "https://yishuwiki.oss-cn-beijing.aliyuncs.com/Operator/HistoricalEvent/2024/09/20240912155733618.png"
  },
  {
    "id": "66b45021942c7eb28beebc0b",
    "periodId": "modern_early",
    "streamId": "s_modern_early",
    "titleEn": "容庚《金文续编》刊行",
    "titleCn": "容庚《金文续编》刊行",
    "date": {
      "year": 1935
    },
    "importance": 4,
    "tags": [
      "近代",
      "金文 / Bronze Script"
    ],
    "meta": {
      "dynasty": "近代",
      "traditionalDate": "民国二十四年",
      "person": "容庚",
      "style": "金文 / Bronze Script",
      "sourceOrder": 1825
    },
    "creatorCn": "容庚",
    "imageUrl": "https://yishuwiki.oss-cn-beijing.aliyuncs.com/Operator/HistoricalEvent/2024/09/20240912161221476.png",
    "descriptionCn": "容庚《金文续编》由商务印书馆刊行"
  },
  {
    "id": "66b45021942c7eb28beebc0c",
    "periodId": "modern_early",
    "streamId": "s_modern_early",
    "titleEn": "白蕉撰《书法十讲》",
    "titleCn": "白蕉撰《书法十讲》",
    "date": {
      "year": 1936
    },
    "importance": 4,
    "tags": [
      "近代",
      "书论与收藏 / Theory and Connoisseurship"
    ],
    "meta": {
      "dynasty": "近代",
      "traditionalDate": "",
      "person": "白蕉",
      "style": "书论与收藏 / Theory and Connoisseurship",
      "sourceOrder": 1826
    },
    "endDate": {
      "year": 1938
    },
    "creatorCn": "白蕉",
    "imageUrl": "https://yishuwiki.oss-cn-beijing.aliyuncs.com/Operator/HistoricalEvent/2024/09/20240912161753865.png"
  },
  {
    "id": "66b45021942c7eb28beebc0d",
    "periodId": "modern_early",
    "streamId": "s_modern_early",
    "titleEn": "章太炎书《孙衡甫六十寿序》",
    "titleCn": "章太炎书《孙衡甫六十寿序》",
    "date": {
      "year": 1936,
      "accuracy": "not_after"
    },
    "importance": 4,
    "tags": [
      "近代",
      "书法事件 / Calligraphy Event"
    ],
    "meta": {
      "dynasty": "近代",
      "traditionalDate": "民国二十五年以前",
      "person": "章太炎",
      "style": "书法事件 / Calligraphy Event",
      "sourceOrder": 1827
    },
    "creatorCn": "章太炎",
    "imageUrl": "https://yishuwiki.oss-cn-beijing.aliyuncs.com/Operator/HistoricalEvent/2024/09/20240912162349305.png"
  },
  {
    "id": "66b45021942c7eb28beebc0e",
    "periodId": "modern_early",
    "streamId": "s_modern_early",
    "titleEn": "章太炎书《篆书千文》",
    "titleCn": "章太炎书《篆书千文》",
    "date": {
      "year": 1936,
      "accuracy": "not_after"
    },
    "importance": 4,
    "tags": [
      "近代",
      "篆书 / Seal Script"
    ],
    "meta": {
      "dynasty": "近代",
      "traditionalDate": "民国二十五年以前",
      "person": "章太炎",
      "style": "篆书 / Seal Script",
      "sourceOrder": 1828
    },
    "creatorCn": "章太炎",
    "imageUrl": "https://yishuwiki.oss-cn-beijing.aliyuncs.com/Operator/HistoricalEvent/2024/09/20240912162552017.png"
  },
  {
    "id": "66b45021942c7eb28beebc0f",
    "periodId": "modern_early",
    "streamId": "s_modern_early",
    "titleEn": "于右任出版《标准草书千字文》",
    "titleCn": "于右任出版《标准草书千字文》",
    "date": {
      "year": 1936
    },
    "importance": 4,
    "tags": [
      "近代",
      "草书 / Cursive Script"
    ],
    "meta": {
      "dynasty": "近代",
      "traditionalDate": "民国二十五年",
      "person": "于右任",
      "style": "草书 / Cursive Script",
      "sourceOrder": 1829
    },
    "creatorCn": "于右任",
    "imageUrl": "https://yishuwiki.oss-cn-beijing.aliyuncs.com/Operator/HistoricalEvent/2024/09/20240912163105187.png"
  },
  {
    "id": "66b45021942c7eb28beebc10",
    "periodId": "modern_early",
    "streamId": "s_modern_early",
    "titleEn": "顾廷龙撰《古陶文孴录》",
    "titleCn": "顾廷龙撰《古陶文孴录》",
    "date": {
      "year": 1936
    },
    "importance": 4,
    "tags": [
      "近代",
      "书论与收藏 / Theory and Connoisseurship"
    ],
    "meta": {
      "dynasty": "近代",
      "traditionalDate": "民国二十五年",
      "person": "顾廷龙",
      "style": "书论与收藏 / Theory and Connoisseurship",
      "sourceOrder": 1830
    },
    "creatorCn": "顾廷龙",
    "imageUrl": "https://yishuwiki.oss-cn-beijing.aliyuncs.com/Operator/HistoricalEvent/2024/09/20240912163436479.png"
  },
  {
    "id": "66b45021942c7eb28beebc11",
    "periodId": "modern_early",
    "streamId": "s_modern_early",
    "titleEn": "于辅之书《题黄山天都峰望云海小影轴》",
    "titleCn": "于辅之书《题黄山天都峰望云海小影轴》",
    "date": {
      "year": 1936
    },
    "importance": 5,
    "tags": [
      "近代",
      "书法事件 / Calligraphy Event"
    ],
    "meta": {
      "dynasty": "近代",
      "traditionalDate": "民国二十五年",
      "person": "于辅之",
      "style": "书法事件 / Calligraphy Event",
      "sourceOrder": 1831
    },
    "creatorCn": "于辅之"
  },
  {
    "id": "66b45021942c7eb28beebc12",
    "periodId": "modern_early",
    "streamId": "s_modern_early",
    "titleEn": "弘一法师书《行书集华严经偈句》",
    "titleCn": "弘一法师书《行书集华严经偈句》",
    "date": {
      "year": 1936
    },
    "importance": 4,
    "tags": [
      "近代",
      "行书 / Running Script"
    ],
    "meta": {
      "dynasty": "近代",
      "traditionalDate": "民国二十五年",
      "person": "弘一法师",
      "style": "行书 / Running Script",
      "sourceOrder": 1832
    },
    "creatorCn": "弘一法师",
    "imageUrl": "https://yishuwiki.oss-cn-beijing.aliyuncs.com/Operator/HistoricalEvent/2024/09/20240912170124364.png"
  },
  {
    "id": "66b45021942c7eb28beebc13",
    "periodId": "modern_early",
    "streamId": "s_modern_early",
    "titleEn": "徐悲鸿书《岂有蛟龙诗轴》",
    "titleCn": "徐悲鸿书《岂有蛟龙诗轴》",
    "date": {
      "year": 1937
    },
    "importance": 4,
    "tags": [
      "近代",
      "书法事件 / Calligraphy Event"
    ],
    "meta": {
      "dynasty": "近代",
      "traditionalDate": "民国二十六年",
      "person": "徐悲鸿",
      "style": "书法事件 / Calligraphy Event",
      "sourceOrder": 1833
    },
    "creatorCn": "徐悲鸿",
    "imageUrl": "https://yishuwiki.oss-cn-beijing.aliyuncs.com/Operator/HistoricalEvent/2024/09/20240912170513423.png"
  },
  {
    "id": "66b45021942c7eb28beebc14",
    "periodId": "modern_early",
    "streamId": "s_modern_early",
    "titleEn": "吴玉如书《赠振华仁兄草书七言联》",
    "titleCn": "吴玉如书《赠振华仁兄草书七言联》",
    "date": {
      "year": 1937
    },
    "importance": 4,
    "tags": [
      "近代",
      "草书 / Cursive Script"
    ],
    "meta": {
      "dynasty": "近代",
      "traditionalDate": "民国二十六年",
      "person": "吴玉如",
      "style": "草书 / Cursive Script",
      "sourceOrder": 1834
    },
    "creatorCn": "吴玉如",
    "imageUrl": "https://yishuwiki.oss-cn-beijing.aliyuncs.com/Operator/HistoricalEvent/2024/09/20240912171058576.png"
  },
  {
    "id": "66b45021942c7eb28beebc15",
    "periodId": "modern_early",
    "streamId": "s_modern_early",
    "titleEn": "中国印学社辑《吴昌硕印谱》",
    "titleCn": "中国印学社辑《吴昌硕印谱》",
    "date": {
      "year": 1937
    },
    "importance": 4,
    "tags": [
      "近代",
      "篆刻与印学 / Seal Carving"
    ],
    "meta": {
      "dynasty": "近代",
      "traditionalDate": "民国二十六年",
      "person": "",
      "style": "篆刻与印学 / Seal Carving",
      "sourceOrder": 1835
    },
    "imageUrl": "https://yishuwiki.oss-cn-beijing.aliyuncs.com/Operator/HistoricalEvent/2024/09/20240912171610983.png"
  },
  {
    "id": "66b45021942c7eb28beebc16",
    "periodId": "modern_early",
    "streamId": "s_modern_early",
    "titleEn": "《商后母戊鼎》出土",
    "titleCn": "《商后母戊鼎》出土",
    "date": {
      "year": 1939
    },
    "importance": 4,
    "tags": [
      "近代",
      "书法事件 / Calligraphy Event"
    ],
    "meta": {
      "dynasty": "近代",
      "traditionalDate": "民国二十八年",
      "person": "",
      "style": "书法事件 / Calligraphy Event",
      "sourceOrder": 1836
    },
    "imageUrl": "https://yishuwiki.oss-cn-beijing.aliyuncs.com/Operator/HistoricalEvent/2024/09/20240912171712310.png",
    "descriptionCn": "河南安阳武官村商代大墓出土《商后母戊鼎》"
  },
  {
    "id": "66b45021942c7eb28beebc17",
    "periodId": "modern_early",
    "streamId": "s_modern_early",
    "titleEn": "余绍宋书《赠左高仁兄诗轴》",
    "titleCn": "余绍宋书《赠左高仁兄诗轴》",
    "date": {
      "year": 1939
    },
    "importance": 4,
    "tags": [
      "近代",
      "书法事件 / Calligraphy Event"
    ],
    "meta": {
      "dynasty": "近代",
      "traditionalDate": "民国二十八年",
      "person": "余绍宋",
      "style": "书法事件 / Calligraphy Event",
      "sourceOrder": 1837
    },
    "creatorCn": "余绍宋",
    "imageUrl": "https://yishuwiki.oss-cn-beijing.aliyuncs.com/Operator/HistoricalEvent/2024/09/20240912172909226.png"
  },
  {
    "id": "66b45021942c7eb28beebc18",
    "periodId": "modern_early",
    "streamId": "s_modern_early",
    "titleEn": "白蕉书《赠立鼎先生书轴》",
    "titleCn": "白蕉书《赠立鼎先生书轴》",
    "date": {
      "year": 1940
    },
    "importance": 4,
    "tags": [
      "近代",
      "书法事件 / Calligraphy Event"
    ],
    "meta": {
      "dynasty": "近代",
      "traditionalDate": "民国二十九年",
      "person": "白蕉",
      "style": "书法事件 / Calligraphy Event",
      "sourceOrder": 1838
    },
    "creatorCn": "白蕉",
    "imageUrl": "https://yishuwiki.oss-cn-beijing.aliyuncs.com/Operator/HistoricalEvent/2024/09/20240912173036005.png"
  },
  {
    "id": "66b45021942c7eb28beebc19",
    "periodId": "modern_early",
    "streamId": "s_modern_early",
    "titleEn": "弘一法师书《念佛不忘救国横披》",
    "titleCn": "弘一法师书《念佛不忘救国横披》",
    "date": {
      "year": 1940
    },
    "importance": 4,
    "tags": [
      "近代",
      "书法事件 / Calligraphy Event"
    ],
    "meta": {
      "dynasty": "近代",
      "traditionalDate": "民国二十九年",
      "person": "弘一法师",
      "style": "书法事件 / Calligraphy Event",
      "sourceOrder": 1839
    },
    "creatorCn": "弘一法师",
    "imageUrl": "https://yishuwiki.oss-cn-beijing.aliyuncs.com/Operator/HistoricalEvent/2024/09/20240912173153527.png"
  },
  {
    "id": "66b45021942c7eb28beebc1a",
    "periodId": "modern_early",
    "streamId": "s_modern_early",
    "titleEn": "罗振玉书《贞松堂藏历代名人法书》",
    "titleCn": "罗振玉书《贞松堂藏历代名人法书》",
    "date": {
      "year": 1940,
      "accuracy": "not_after"
    },
    "importance": 4,
    "tags": [
      "近代",
      "书论与收藏 / Theory and Connoisseurship"
    ],
    "meta": {
      "dynasty": "近代",
      "traditionalDate": "民国二十九年以前",
      "person": "罗振玉",
      "style": "书论与收藏 / Theory and Connoisseurship",
      "sourceOrder": 1840
    },
    "creatorCn": "罗振玉",
    "imageUrl": "https://yishuwiki.oss-cn-beijing.aliyuncs.com/Operator/HistoricalEvent/2024/09/20240912173258528.png"
  },
  {
    "id": "66b45021942c7eb28beebc1b",
    "periodId": "modern_early",
    "streamId": "s_modern_early",
    "titleEn": "罗振玉书《百爵斋藏历代名人法书》",
    "titleCn": "罗振玉书《百爵斋藏历代名人法书》",
    "date": {
      "year": 1940,
      "accuracy": "not_after"
    },
    "importance": 4,
    "tags": [
      "近代",
      "书论与收藏 / Theory and Connoisseurship"
    ],
    "meta": {
      "dynasty": "近代",
      "traditionalDate": "民国二十九年以前",
      "person": "罗振玉",
      "style": "书论与收藏 / Theory and Connoisseurship",
      "sourceOrder": 1841
    },
    "creatorCn": "罗振玉",
    "imageUrl": "https://yishuwiki.oss-cn-beijing.aliyuncs.com/Operator/HistoricalEvent/2024/09/20240912173330740.png"
  },
  {
    "id": "66b45021942c7eb28beebc1c",
    "periodId": "modern_early",
    "streamId": "s_modern_early",
    "titleEn": "于右任创辨《草书月刊》",
    "titleCn": "于右任创辨《草书月刊》",
    "date": {
      "year": 1941
    },
    "importance": 4,
    "tags": [
      "近代",
      "草书 / Cursive Script"
    ],
    "meta": {
      "dynasty": "近代",
      "traditionalDate": "民国三十年",
      "person": "于右任",
      "style": "草书 / Cursive Script",
      "sourceOrder": 1842
    },
    "creatorCn": "于右任",
    "imageUrl": "https://yishuwiki.oss-cn-beijing.aliyuncs.com/Operator/HistoricalEvent/2024/09/20240912173435596.png",
    "descriptionCn": "于右任创辨《草书月刊》，共出四期"
  },
  {
    "id": "66b45022942c7eb28beebc1d",
    "periodId": "modern_early",
    "streamId": "s_modern_early",
    "titleEn": "商衍鎏书《心经轴》",
    "titleCn": "商衍鎏书《心经轴》",
    "date": {
      "year": 1941
    },
    "importance": 4,
    "tags": [
      "近代",
      "书法事件 / Calligraphy Event"
    ],
    "meta": {
      "dynasty": "近代",
      "traditionalDate": "民国三十年",
      "person": "商衍鎏",
      "style": "书法事件 / Calligraphy Event",
      "sourceOrder": 1843
    },
    "creatorCn": "商衍鎏",
    "imageUrl": "https://yishuwiki.oss-cn-beijing.aliyuncs.com/Operator/HistoricalEvent/2024/09/20240912173952026.png"
  },
  {
    "id": "66b45022942c7eb28beebc1e",
    "periodId": "modern_early",
    "streamId": "s_modern_early",
    "titleEn": "陕西岐山出土《禹鼎》",
    "titleCn": "陕西岐山出土《禹鼎》",
    "date": {
      "year": 1942
    },
    "importance": 4,
    "tags": [
      "近代",
      "书法事件 / Calligraphy Event"
    ],
    "meta": {
      "dynasty": "近代",
      "traditionalDate": "民国三十一年",
      "person": "",
      "style": "书法事件 / Calligraphy Event",
      "sourceOrder": 1844
    },
    "imageUrl": "https://yishuwiki.oss-cn-beijing.aliyuncs.com/Operator/HistoricalEvent/2024/09/20240912174110919.png"
  },
  {
    "id": "66b45022942c7eb28beebc1f",
    "periodId": "modern_early",
    "streamId": "s_modern_early",
    "titleEn": "邓散木辑《厕简楼印存》",
    "titleCn": "邓散木辑《厕简楼印存》",
    "date": {
      "year": 1943
    },
    "importance": 4,
    "tags": [
      "近代",
      "书法事件 / Calligraphy Event"
    ],
    "meta": {
      "dynasty": "近代",
      "traditionalDate": "民国三十二年",
      "person": "邓散木",
      "style": "书法事件 / Calligraphy Event",
      "sourceOrder": 1845
    },
    "creatorCn": "邓散木",
    "imageUrl": "https://yishuwiki.oss-cn-beijing.aliyuncs.com/Operator/HistoricalEvent/2024/09/20240912174324912.png",
    "descriptionCn": "邓散木辑自刻印成《厕简楼印存》四册。"
  },
  {
    "id": "66b45022942c7eb28beebc20",
    "periodId": "modern_early",
    "streamId": "s_modern_early",
    "titleEn": "沈子善等创办《书学》杂志",
    "titleCn": "沈子善等创办《书学》杂志",
    "date": {
      "year": 1943
    },
    "importance": 4,
    "tags": [
      "近代",
      "书法事件 / Calligraphy Event"
    ],
    "meta": {
      "dynasty": "近代",
      "traditionalDate": "民国三十二年",
      "person": "沈子善",
      "style": "书法事件 / Calligraphy Event",
      "sourceOrder": 1846
    },
    "creatorCn": "沈子善",
    "imageUrl": "https://yishuwiki.oss-cn-beijing.aliyuncs.com/Operator/HistoricalEvent/2024/09/20240912174623338.png",
    "descriptionCn": "沈子善等创办之《书学》杂志刊行，四期后停刊（1945）年。"
  },
  {
    "id": "66b45022942c7eb28beebc21",
    "periodId": "modern_early",
    "streamId": "s_modern_early",
    "titleEn": "徐悲鸿书《赠华度四言联》",
    "titleCn": "徐悲鸿书《赠华度四言联》",
    "date": {
      "year": 1943
    },
    "importance": 4,
    "tags": [
      "近代",
      "书法事件 / Calligraphy Event"
    ],
    "meta": {
      "dynasty": "近代",
      "traditionalDate": "民国三十二年",
      "person": "徐悲鸿",
      "style": "书法事件 / Calligraphy Event",
      "sourceOrder": 1847
    },
    "creatorCn": "徐悲鸿",
    "imageUrl": "https://yishuwiki.oss-cn-beijing.aliyuncs.com/Operator/HistoricalEvent/2024/09/20240912174814975.png"
  },
  {
    "id": "66b45022942c7eb28beebc22",
    "periodId": "modern_early",
    "streamId": "s_modern_early",
    "titleEn": "谢无量书《孟晋斋题匾》",
    "titleCn": "谢无量书《孟晋斋题匾》",
    "date": {
      "year": 1945
    },
    "importance": 4,
    "tags": [
      "近代",
      "书法事件 / Calligraphy Event"
    ],
    "meta": {
      "dynasty": "近代",
      "traditionalDate": "民国三十四年",
      "person": "谢无量",
      "style": "书法事件 / Calligraphy Event",
      "sourceOrder": 1848
    },
    "creatorCn": "谢无量",
    "imageUrl": "https://yishuwiki.oss-cn-beijing.aliyuncs.com/Operator/HistoricalEvent/2024/09/20240912175239079.png"
  },
  {
    "id": "66b45022942c7eb28beebc23",
    "periodId": "modern_early",
    "streamId": "s_modern_early",
    "titleEn": "容庚书《考释古文字识语》",
    "titleCn": "容庚书《考释古文字识语》",
    "date": {
      "year": 1945
    },
    "importance": 4,
    "tags": [
      "近代",
      "书法事件 / Calligraphy Event"
    ],
    "meta": {
      "dynasty": "近代",
      "traditionalDate": "民国三十四年",
      "person": "容庚",
      "style": "书法事件 / Calligraphy Event",
      "sourceOrder": 1849
    },
    "creatorCn": "容庚",
    "imageUrl": "https://yishuwiki.oss-cn-beijing.aliyuncs.com/Operator/HistoricalEvent/2024/09/20240912175602827.png"
  },
  {
    "id": "66b45022942c7eb28beebc24",
    "periodId": "modern_early",
    "streamId": "s_modern_early",
    "titleEn": "高二适书《东轩诗轴》",
    "titleCn": "高二适书《东轩诗轴》",
    "date": {
      "year": 1945
    },
    "importance": 4,
    "tags": [
      "近代",
      "书法事件 / Calligraphy Event"
    ],
    "meta": {
      "dynasty": "近代",
      "traditionalDate": "民国三十四年",
      "person": "高二适",
      "style": "书法事件 / Calligraphy Event",
      "sourceOrder": 1850
    },
    "creatorCn": "高二适",
    "imageUrl": "https://yishuwiki.oss-cn-beijing.aliyuncs.com/Operator/HistoricalEvent/2024/09/20240912175841566.png"
  },
  {
    "id": "66b45022942c7eb28beebc25",
    "periodId": "modern_early",
    "streamId": "s_modern_early",
    "titleEn": "潘天寿书《赠鸿逵研弟诗轴》",
    "titleCn": "潘天寿书《赠鸿逵研弟诗轴》",
    "date": {
      "year": 1947
    },
    "importance": 4,
    "tags": [
      "近代",
      "书法事件 / Calligraphy Event"
    ],
    "meta": {
      "dynasty": "近代",
      "traditionalDate": "民国三十六年",
      "person": "潘天寿",
      "style": "书法事件 / Calligraphy Event",
      "sourceOrder": 1851
    },
    "creatorCn": "潘天寿",
    "imageUrl": "https://yishuwiki.oss-cn-beijing.aliyuncs.com/Operator/HistoricalEvent/2024/09/20240912175946792.png"
  },
  {
    "id": "66b45022942c7eb28beebc26",
    "periodId": "modern_early",
    "streamId": "s_modern_early",
    "titleEn": "张大千书《赠农雨行书七言联》",
    "titleCn": "张大千书《赠农雨行书七言联》",
    "date": {
      "year": 1947
    },
    "importance": 4,
    "tags": [
      "近代",
      "行书 / Running Script"
    ],
    "meta": {
      "dynasty": "近代",
      "traditionalDate": "民国三十六年",
      "person": "张大千",
      "style": "行书 / Running Script",
      "sourceOrder": 1852
    },
    "creatorCn": "张大千",
    "imageUrl": "https://yishuwiki.oss-cn-beijing.aliyuncs.com/Operator/HistoricalEvent/2024/09/20240913094455861.png"
  },
  {
    "id": "66b45022942c7eb28beebc27",
    "periodId": "modern_early",
    "streamId": "s_modern_early",
    "titleEn": "沈尹默撰《晋王右军题笔阵图后》",
    "titleCn": "沈尹默撰《晋王右军题笔阵图后》",
    "date": {
      "year": 1947
    },
    "importance": 4,
    "tags": [
      "近代",
      "书论与收藏 / Theory and Connoisseurship"
    ],
    "meta": {
      "dynasty": "近代",
      "traditionalDate": "民国三十六年",
      "person": "沈尹默",
      "style": "书论与收藏 / Theory and Connoisseurship",
      "sourceOrder": 1853
    },
    "creatorCn": "沈尹默",
    "imageUrl": "https://yishuwiki.oss-cn-beijing.aliyuncs.com/Operator/HistoricalEvent/2024/09/20240913094608182.png"
  },
  {
    "id": "66b45022942c7eb28beebc28",
    "periodId": "modern_early",
    "streamId": "s_modern_early",
    "titleEn": "王福庵书节录《文心雕龙》隶书条幅",
    "titleCn": "王福庵书节录《文心雕龙》隶书条幅",
    "date": {
      "year": 1948
    },
    "importance": 4,
    "tags": [
      "近代",
      "隶书与汉碑 / Clerical Script"
    ],
    "meta": {
      "dynasty": "近代",
      "traditionalDate": "民国三十七年",
      "person": "王福庵",
      "style": "隶书与汉碑 / Clerical Script",
      "sourceOrder": 1854
    },
    "creatorCn": "王福庵",
    "imageUrl": "https://yishuwiki.oss-cn-beijing.aliyuncs.com/Operator/HistoricalEvent/2024/09/20240913094718198.png"
  },
  {
    "id": "66b45022942c7eb28beebc29",
    "periodId": "modern_early",
    "streamId": "s_modern_early",
    "titleEn": "吴稚晖书《行书七言联》",
    "titleCn": "吴稚晖书《行书七言联》",
    "date": {
      "year": 1948
    },
    "importance": 4,
    "tags": [
      "近代",
      "行书 / Running Script"
    ],
    "meta": {
      "dynasty": "近代",
      "traditionalDate": "民国三十七年",
      "person": "吴稚晖",
      "style": "行书 / Running Script",
      "sourceOrder": 1855
    },
    "creatorCn": "吴稚晖",
    "imageUrl": "https://yishuwiki.oss-cn-beijing.aliyuncs.com/Operator/HistoricalEvent/2024/11/20241126165832404.png"
  },
  {
    "id": "66b45022942c7eb28beebc2a",
    "periodId": "modern_early",
    "streamId": "s_modern_early",
    "titleEn": "张大千书《三年万里行书七言联》",
    "titleCn": "张大千书《三年万里行书七言联》",
    "date": {
      "year": 1948
    },
    "importance": 4,
    "tags": [
      "近代",
      "行书 / Running Script"
    ],
    "meta": {
      "dynasty": "近代",
      "traditionalDate": "民国三十七年",
      "person": "张大千",
      "style": "行书 / Running Script",
      "sourceOrder": 1856
    },
    "creatorCn": "张大千",
    "imageUrl": "https://yishuwiki.oss-cn-beijing.aliyuncs.com/Operator/HistoricalEvent/2024/11/20241127095138226.png"
  },
  {
    "id": "66b45022942c7eb28beebc2b",
    "periodId": "modern",
    "streamId": "s_modern",
    "titleEn": "沈尹默发表《沈尹默论书丛稿》",
    "titleCn": "沈尹默发表《沈尹默论书丛稿》",
    "date": {
      "year": 1949
    },
    "importance": 4,
    "tags": [
      "现代",
      "书法事件 / Calligraphy Event"
    ],
    "meta": {
      "dynasty": "现代",
      "traditionalDate": "",
      "person": "沈尹默",
      "style": "书法事件 / Calligraphy Event",
      "sourceOrder": 1857
    },
    "creatorCn": "沈尹默",
    "imageUrl": "https://yishuwiki.oss-cn-beijing.aliyuncs.com/Operator/HistoricalEvent/2024/11/20241127101421686.png"
  },
  {
    "id": "66b45022942c7eb28beebc2c",
    "periodId": "modern",
    "streamId": "s_modern",
    "titleEn": "董作宾成《殷虚文字》甲、乙编",
    "titleCn": "董作宾成《殷虚文字》甲、乙编",
    "date": {
      "year": 1949
    },
    "importance": 4,
    "tags": [
      "现代",
      "甲骨文 / Oracle-bone Script"
    ],
    "meta": {
      "dynasty": "现代",
      "traditionalDate": "",
      "person": "董作宾",
      "style": "甲骨文 / Oracle-bone Script",
      "sourceOrder": 1858
    },
    "creatorCn": "董作宾",
    "imageUrl": "https://yishuwiki.oss-cn-beijing.aliyuncs.com/Operator/HistoricalEvent/2024/11/20241127101411448.png",
    "descriptionCn": "董作宾成《殷虚文字》甲、乙编。按：此前董氏首为殷虚甲骨文字划分断代五期，分析其书法风格之时代特征。"
  },
  {
    "id": "66b45022942c7eb28beebc2d",
    "periodId": "modern",
    "streamId": "s_modern",
    "titleEn": "谢无量书《夜坐偶咏扇面》",
    "titleCn": "谢无量书《夜坐偶咏扇面》",
    "date": {
      "year": 1949
    },
    "importance": 4,
    "tags": [
      "现代",
      "书法事件 / Calligraphy Event"
    ],
    "meta": {
      "dynasty": "现代",
      "traditionalDate": "",
      "person": "谢无量",
      "style": "书法事件 / Calligraphy Event",
      "sourceOrder": 1859
    },
    "creatorCn": "谢无量",
    "imageUrl": "https://yishuwiki.oss-cn-beijing.aliyuncs.com/Operator/HistoricalEvent/2024/11/20241127101402701.png"
  }
]
